{"nom":"Lot","communes":[{"code":"46001","nom":"Albas","inscrits":480,"votants":379,"participation":78.96,"status":"elu","bord":"indecis","candidats":[{"nom":"Albas en action","parti":"Albas en action","bord":"Divers","score":62.26,"color":"var(--div)"},{"nom":"Toutes les voix d'Albas","parti":"Toutes les voix d'Albas","bord":"Divers","score":37.74,"color":"var(--div)"}]},{"code":"46002","nom":"Albiac","inscrits":102,"votants":75,"participation":73.53,"status":"elu","bord":"indecis","candidats":[{"nom":"ENSEMBLE, FAISONS VIVRE NOTRE VILLAGE","parti":"ENSEMBLE, FAISONS VIVRE NOTRE VILLAGE","bord":"Divers","score":100.0,"color":"var(--div)"}]},{"code":"46003","nom":"Alvignac","inscrits":571,"votants":370,"participation":64.8,"status":"elu","bord":"indecis","candidats":[{"nom":"ALVIGNAC, NOTRE VILLAGE, UN AVENIR...","parti":"ALVIGNAC, NOTRE VILLAGE, UN AVENIR...","bord":"Divers","score":100.0,"color":"var(--div)"}]},{"code":"46004","nom":"Anglars","inscrits":192,"votants":125,"participation":65.1,"status":"elu","bord":"indecis","candidats":[{"nom":"ANGLARS NOTRE VILLAGE","parti":"ANGLARS NOTRE VILLAGE","bord":"Divers","score":100.0,"color":"var(--div)"}]},{"code":"46005","nom":"Anglars-Juillac","inscrits":262,"votants":163,"participation":62.21,"status":"elu","bord":"indecis","candidats":[{"nom":"Demain commence aujourd'hui","parti":"Demain commence aujourd'hui","bord":"Divers","score":100.0,"color":"var(--div)"}]},{"code":"46006","nom":"Anglars-Nozac","inscrits":364,"votants":203,"participation":55.77,"status":"elu","bord":"indecis","candidats":[{"nom":"AGIR ENSEMBLE POUR ANGLARS-NOZAC","parti":"AGIR ENSEMBLE POUR ANGLARS-NOZAC","bord":"Divers","score":100.0,"color":"var(--div)"}]},{"code":"46007","nom":"Arcambal","inscrits":765,"votants":401,"participation":52.42,"status":"elu","bord":"indecis","candidats":[{"nom":"Arcambal, village vivant, village uni !","parti":"Arcambal, village vivant, village uni !","bord":"Divers","score":100.0,"color":"var(--div)"}]},{"code":"46008","nom":"Les Arques","inscrits":193,"votants":130,"participation":67.36,"status":"elu","bord":"indecis","candidats":[{"nom":"TOUS UNIS POUR LES ARQUES","parti":"TOUS UNIS POUR LES ARQUES","bord":"Divers","score":100.0,"color":"var(--div)"}]},{"code":"46009","nom":"Assier","inscrits":569,"votants":449,"participation":78.91,"status":"elu","bord":"indecis","candidats":[{"nom":"BIEN VIVRE ASSIER 2026","parti":"BIEN VIVRE ASSIER 2026","bord":"Divers","score":64.16,"color":"var(--div)"},{"nom":"Faire village","parti":"Faire village","bord":"Divers","score":35.84,"color":"var(--div)"}]},{"code":"46010","nom":"Aujols","inscrits":318,"votants":208,"participation":65.41,"status":"elu","bord":"indecis","candidats":[{"nom":"Unis pour notre village","parti":"Unis pour notre village","bord":"Divers","score":100.0,"color":"var(--div)"}]},{"code":"46011","nom":"Autoire","inscrits":328,"votants":289,"participation":88.11,"status":"elu","bord":"indecis","candidats":[{"nom":"AUTOIRE CONTINUITE ET NOUVEL ELAN","parti":"AUTOIRE CONTINUITE ET NOUVEL ELAN","bord":"Divers","score":54.68,"color":"var(--div)"},{"nom":"AUTOIRE POURSUIVONS L'HISTOIRE","parti":"AUTOIRE POURSUIVONS L'HISTOIRE","bord":"Divers","score":45.32,"color":"var(--div)"}]},{"code":"46012","nom":"Aynac","inscrits":466,"votants":318,"participation":68.24,"status":"elu","bord":"indecis","candidats":[{"nom":"AYNAC AVENIR","parti":"AYNAC AVENIR","bord":"Divers","score":100.0,"color":"var(--div)"}]},{"code":"46013","nom":"Bach","inscrits":195,"votants":135,"participation":69.23,"status":"elu","bord":"indecis","candidats":[{"nom":"Bach, bien vivre ensemble","parti":"Bach, bien vivre ensemble","bord":"Divers","score":100.0,"color":"var(--div)"}]},{"code":"46015","nom":"Bagnac-sur-Célé","inscrits":1213,"votants":681,"participation":56.14,"status":"elu","bord":"indecis","candidats":[{"nom":"BAGNAC D'HIER A DEMAIN","parti":"BAGNAC D'HIER A DEMAIN","bord":"Divers","score":100.0,"color":"var(--div)"}]},{"code":"46016","nom":"Baladou","inscrits":350,"votants":269,"participation":76.86,"status":"elu","bord":"indecis","candidats":[{"nom":"BALADOU ENSEMBLE","parti":"BALADOU ENSEMBLE","bord":"Divers","score":61.6,"color":"var(--div)"},{"nom":"UNE NOUVELLE NOTE POUR BALADOU","parti":"UNE NOUVELLE NOTE POUR BALADOU","bord":"Divers","score":38.4,"color":"var(--div)"}]},{"code":"46017","nom":"Bannes","inscrits":129,"votants":99,"participation":76.74,"status":"elu","bord":"indecis","candidats":[{"nom":"BANNES 2026","parti":"BANNES 2026","bord":"Divers","score":100.0,"color":"var(--div)"}]},{"code":"46018","nom":"Le Bastit","inscrits":140,"votants":99,"participation":70.71,"status":"elu","bord":"indecis","candidats":[{"nom":"VIVRE ENSEMBLE AU BASTIT","parti":"VIVRE ENSEMBLE AU BASTIT","bord":"Divers","score":100.0,"color":"var(--div)"}]},{"code":"46020","nom":"Beauregard","inscrits":241,"votants":172,"participation":71.37,"status":"elu","bord":"indecis","candidats":[{"nom":"Ensemble, pour Beauregard","parti":"Ensemble, pour Beauregard","bord":"Divers","score":100.0,"color":"var(--div)"}]},{"code":"46021","nom":"Béduer","inscrits":618,"votants":411,"participation":66.5,"status":"elu","bord":"indecis","candidats":[{"nom":"LISTE D'UNION POUR BEDUER 2026","parti":"LISTE D'UNION POUR BEDUER 2026","bord":"Divers","score":100.0,"color":"var(--div)"}]},{"code":"46022","nom":"Bélaye","inscrits":195,"votants":177,"participation":90.77,"status":"elu","bord":"indecis","candidats":[{"nom":"Bélaye, l'avenir ensemble","parti":"Bélaye, l'avenir ensemble","bord":"Divers","score":50.29,"color":"var(--div)"},{"nom":"Bien vivre ensemble","parti":"Bien vivre ensemble","bord":"Divers","score":49.71,"color":"var(--div)"}]},{"code":"46023","nom":"Belfort-du-Quercy","inscrits":393,"votants":261,"participation":66.41,"status":"elu","bord":"indecis","candidats":[{"nom":"Ensemble pour Belfort","parti":"Ensemble pour Belfort","bord":"Divers","score":100.0,"color":"var(--div)"}]},{"code":"46024","nom":"Belmont-Bretenoux","inscrits":342,"votants":281,"participation":82.16,"status":"elu","bord":"indecis","candidats":[{"nom":"Continuons pour le développement de Belmont","parti":"Continuons pour le développement de Belmont","bord":"Divers","score":55.35,"color":"var(--div)"},{"nom":"BELMONT, UNIS POUR L'AVENIR","parti":"BELMONT, UNIS POUR L'AVENIR","bord":"Divers","score":44.65,"color":"var(--div)"}]},{"code":"46026","nom":"Belmont-Sainte-Foi","inscrits":141,"votants":114,"participation":80.85,"status":"elu","bord":"indecis","candidats":[{"nom":"Bien vivre à Belmont Sainte Foi","parti":"Bien vivre à Belmont Sainte Foi","bord":"Divers","score":100.0,"color":"var(--div)"}]},{"code":"46027","nom":"Berganty","inscrits":131,"votants":93,"participation":70.99,"status":"elu","bord":"indecis","candidats":[{"nom":"Berganty avenir","parti":"Berganty avenir","bord":"Divers","score":100.0,"color":"var(--div)"}]},{"code":"46028","nom":"Bétaille","inscrits":828,"votants":597,"participation":72.1,"status":"elu","bord":"indecis","candidats":[{"nom":"LISTE D'UNION COMMUNALE","parti":"LISTE D'UNION COMMUNALE","bord":"Divers","score":79.08,"color":"var(--div)"},{"nom":"TOUS ENSEMBLE POUR BÉTAILLE","parti":"TOUS ENSEMBLE POUR BÉTAILLE","bord":"Divers","score":20.92,"color":"var(--div)"}]},{"code":"46029","nom":"Biars-sur-Cère","inscrits":1352,"votants":941,"participation":69.6,"status":"elu","bord":"indecis","candidats":[{"nom":"NOUS POUR VOUS ENSEMBLE","parti":"NOUS POUR VOUS ENSEMBLE","bord":"Divers","score":73.01,"color":"var(--div)"},{"nom":"ENSEMBLE POUR BIARS","parti":"ENSEMBLE POUR BIARS","bord":"Divers","score":26.99,"color":"var(--div)"}]},{"code":"46030","nom":"Bio","inscrits":340,"votants":227,"participation":66.76,"status":"elu","bord":"indecis","candidats":[{"nom":"BIEN VIVRE À BIO","parti":"BIEN VIVRE À BIO","bord":"Divers","score":100.0,"color":"var(--div)"}]},{"code":"46031","nom":"Blars","inscrits":110,"votants":76,"participation":69.09,"status":"elu","bord":"indecis","candidats":[{"nom":"ÉQUIPE BLARSOISE 2026","parti":"ÉQUIPE BLARSOISE 2026","bord":"Divers","score":100.0,"color":"var(--div)"}]},{"code":"46032","nom":"Boissières","inscrits":327,"votants":196,"participation":59.94,"status":"elu","bord":"indecis","candidats":[{"nom":"Boissières, poursuivons la dynamique","parti":"Boissières, poursuivons la dynamique","bord":"Divers","score":100.0,"color":"var(--div)"}]},{"code":"46033","nom":"Porte-du-Quercy","inscrits":474,"votants":298,"participation":62.87,"status":"elu","bord":"indecis","candidats":[{"nom":"Ensemble pour Porte-du-Quercy","parti":"Ensemble pour Porte-du-Quercy","bord":"Divers","score":100.0,"color":"var(--div)"}]},{"code":"46034","nom":"Le Bourg","inscrits":271,"votants":176,"participation":64.94,"status":"elu","bord":"indecis","candidats":[{"nom":"AGIR ENSEMBLE POUR LE BOURG","parti":"AGIR ENSEMBLE POUR LE BOURG","bord":"Divers","score":100.0,"color":"var(--div)"}]},{"code":"46035","nom":"Boussac","inscrits":163,"votants":129,"participation":79.14,"status":"elu","bord":"indecis","candidats":[{"nom":"AVEC VOUS POUR BOUSSAC","parti":"AVEC VOUS POUR BOUSSAC","bord":"Divers","score":100.0,"color":"var(--div)"}]},{"code":"46036","nom":"Le Bouyssou","inscrits":119,"votants":89,"participation":74.79,"status":"elu","bord":"indecis","candidats":[{"nom":"ENSEMBLE POUR LE BOUYSSOU","parti":"ENSEMBLE POUR LE BOUYSSOU","bord":"Divers","score":100.0,"color":"var(--div)"}]},{"code":"46037","nom":"Bouziès","inscrits":83,"votants":54,"participation":65.06,"status":"elu","bord":"indecis","candidats":[{"nom":"Ensemble pour l'avenir de Bouziès","parti":"Ensemble pour l'avenir de Bouziès","bord":"Divers","score":100.0,"color":"var(--div)"}]},{"code":"46038","nom":"Bretenoux","inscrits":1045,"votants":641,"participation":61.34,"status":"elu","bord":"indecis","candidats":[{"nom":"UNIS POUR BRETENOUX","parti":"UNIS POUR BRETENOUX","bord":"Divers","score":100.0,"color":"var(--div)"}]},{"code":"46039","nom":"Brengues","inscrits":168,"votants":118,"participation":70.24,"status":"elu","bord":"indecis","candidats":[{"nom":"VIVRE A BRENGUES","parti":"VIVRE A BRENGUES","bord":"Divers","score":100.0,"color":"var(--div)"}]},{"code":"46040","nom":"Cabrerets","inscrits":193,"votants":167,"participation":86.53,"status":"elu","bord":"indecis","candidats":[{"nom":"Toujours ensemble pour Cabrerets","parti":"Toujours ensemble pour Cabrerets","bord":"Divers","score":60.87,"color":"var(--div)"},{"nom":"Un nouvel élan pour Cabrerets 2026","parti":"Un nouvel élan pour Cabrerets 2026","bord":"Divers","score":39.13,"color":"var(--div)"}]},{"code":"46041","nom":"Cadrieu","inscrits":143,"votants":110,"participation":76.92,"status":"elu","bord":"indecis","candidats":[{"nom":"ENSEMBLE POUR CADRIEU","parti":"ENSEMBLE POUR CADRIEU","bord":"Divers","score":100.0,"color":"var(--div)"}]},{"code":"46042","nom":"Cahors","inscrits":14299,"votants":7284,"participation":50.94,"status":"elu","bord":"gauche","candidats":[{"nom":"Au quotidien et pour demain","parti":"Au quotidien et pour demain","bord":"Gauche","score":59.53,"color":"var(--ps)"},{"nom":"Cahors Espérance","parti":"Cahors Espérance","bord":"Divers","score":23.25,"color":"var(--div)"},{"nom":"Cahors En Commun","parti":"Cahors En Commun","bord":"Extrême gauche","score":17.22,"color":"var(--lfi)"}]},{"code":"46043","nom":"Cahus","inscrits":171,"votants":109,"participation":63.74,"status":"elu","bord":"indecis","candidats":[{"nom":"ENSEMBLE POUR CAHUS","parti":"ENSEMBLE POUR CAHUS","bord":"Divers","score":100.0,"color":"var(--div)"}]},{"code":"46044","nom":"Caillac","inscrits":498,"votants":347,"participation":69.68,"status":"elu","bord":"indecis","candidats":[{"nom":"Caillac au coeur de notre engagement","parti":"Caillac au coeur de notre engagement","bord":"Divers","score":100.0,"color":"var(--div)"}]},{"code":"46045","nom":"Cajarc","inscrits":956,"votants":730,"participation":76.36,"status":"elu","bord":"indecis","candidats":[{"nom":"ENSEMBLE, L'AVENIR DE CAJARC","parti":"ENSEMBLE, L'AVENIR DE CAJARC","bord":"Divers","score":69.74,"color":"var(--div)"},{"nom":"CAJARC AU COEUR","parti":"CAJARC AU COEUR","bord":"Divers","score":30.26,"color":"var(--div)"}]},{"code":"46046","nom":"Calamane","inscrits":415,"votants":327,"participation":78.8,"status":"elu","bord":"indecis","candidats":[{"nom":"Du lien, du bon sens, de l'action","parti":"Du lien, du bon sens, de l'action","bord":"Divers","score":63.19,"color":"var(--div)"},{"nom":"Tous unis pour Calamane","parti":"Tous unis pour Calamane","bord":"Divers","score":36.81,"color":"var(--div)"}]},{"code":"46047","nom":"Calès","inscrits":179,"votants":107,"participation":59.78,"status":"elu","bord":"indecis","candidats":[{"nom":"BIEN VIVRE À CALÈS","parti":"BIEN VIVRE À CALÈS","bord":"Divers","score":100.0,"color":"var(--div)"}]},{"code":"46049","nom":"Calvignac","inscrits":214,"votants":146,"participation":68.22,"status":"elu","bord":"indecis","candidats":[{"nom":"CALVIGNAC TOUS ENSEMBLE","parti":"CALVIGNAC TOUS ENSEMBLE","bord":"Divers","score":100.0,"color":"var(--div)"}]},{"code":"46050","nom":"Cambayrac","inscrits":169,"votants":159,"participation":94.08,"status":"elu","bord":"indecis","candidats":[{"nom":"Ensemble, faisons vivre notre village","parti":"Ensemble, faisons vivre notre village","bord":"Divers","score":51.27,"color":"var(--div)"},{"nom":"Cambayrac, un avenir en commun","parti":"Cambayrac, un avenir en commun","bord":"Divers","score":48.73,"color":"var(--div)"}]},{"code":"46051","nom":"Cambes","inscrits":319,"votants":189,"participation":59.25,"status":"elu","bord":"indecis","candidats":[{"nom":"VIVRE ENSEMBLE A CAMBES","parti":"VIVRE ENSEMBLE A CAMBES","bord":"Divers","score":100.0,"color":"var(--div)"}]},{"code":"46052","nom":"Camboulit","inscrits":218,"votants":159,"participation":72.94,"status":"elu","bord":"indecis","candidats":[{"nom":"BIEN VIVRE A CAMBOULIT","parti":"BIEN VIVRE A CAMBOULIT","bord":"Divers","score":100.0,"color":"var(--div)"}]},{"code":"46053","nom":"Camburat","inscrits":352,"votants":228,"participation":64.77,"status":"elu","bord":"indecis","candidats":[{"nom":"CAMBURAT PROXIMITE ET BON SENS","parti":"CAMBURAT PROXIMITE ET BON SENS","bord":"Divers","score":100.0,"color":"var(--div)"}]},{"code":"46054","nom":"Caniac-du-Causse","inscrits":246,"votants":151,"participation":61.38,"status":"elu","bord":"indecis","candidats":[{"nom":"BIEN VIVRE ENSEMBLE A CANIAC","parti":"BIEN VIVRE ENSEMBLE A CANIAC","bord":"Divers","score":100.0,"color":"var(--div)"}]},{"code":"46055","nom":"Capdenac","inscrits":953,"votants":603,"participation":63.27,"status":"elu","bord":"indecis","candidats":[{"nom":"VOTEZ POUR VOUS","parti":"VOTEZ POUR VOUS","bord":"Divers","score":54.07,"color":"var(--div)"},{"nom":"Capdenac Demain","parti":"Capdenac Demain","bord":"Divers","score":45.93,"color":"var(--div)"}]},{"code":"46056","nom":"Carayac","inscrits":100,"votants":69,"participation":69.0,"status":"elu","bord":"indecis","candidats":[{"nom":"MUNICIPALE 2026","parti":"MUNICIPALE 2026","bord":"Divers","score":100.0,"color":"var(--div)"}]},{"code":"46057","nom":"Cardaillac","inscrits":528,"votants":319,"participation":60.42,"status":"elu","bord":"indecis","candidats":[{"nom":"VIVRE CARDAILLAC","parti":"VIVRE CARDAILLAC","bord":"Divers","score":100.0,"color":"var(--div)"}]},{"code":"46058","nom":"Carennac","inscrits":347,"votants":223,"participation":64.27,"status":"elu","bord":"indecis","candidats":[{"nom":"PRESERVONS ET VALORISONS NOTRE COMMUNE","parti":"PRESERVONS ET VALORISONS NOTRE COMMUNE","bord":"Divers","score":100.0,"color":"var(--div)"}]},{"code":"46059","nom":"Carlucet","inscrits":177,"votants":165,"participation":93.22,"status":"elu","bord":"indecis","candidats":[{"nom":"CULTIVONS LE BIEN VIVRE ENSEMBLE A CARLUCET","parti":"CULTIVONS LE BIEN VIVRE ENSEMBLE A CARLUCET","bord":"Divers","score":58.13,"color":"var(--div)"},{"nom":"AUJOURD'HUI CARLUCET POUR CONSTRUIRE DEMAIN","parti":"AUJOURD'HUI CARLUCET POUR CONSTRUIRE DEMAIN","bord":"Divers","score":41.88,"color":"var(--div)"}]},{"code":"46060","nom":"Carnac-Rouffiac","inscrits":208,"votants":145,"participation":69.71,"status":"elu","bord":"indecis","candidats":[{"nom":"Carnac-Rouffiac 2026","parti":"Carnac-Rouffiac 2026","bord":"Divers","score":100.0,"color":"var(--div)"}]},{"code":"46061","nom":"Cassagnes","inscrits":159,"votants":106,"participation":66.67,"status":"elu","bord":"indecis","candidats":[{"nom":"Bien vivre ensemble à Cassagnes","parti":"Bien vivre ensemble à Cassagnes","bord":"Divers","score":100.0,"color":"var(--div)"}]},{"code":"46062","nom":"Castelfranc","inscrits":280,"votants":189,"participation":67.5,"status":"elu","bord":"indecis","candidats":[{"nom":"Castelfranc 2026","parti":"Castelfranc 2026","bord":"Divers","score":100.0,"color":"var(--div)"}]},{"code":"46063","nom":"Castelnau-Montratier","inscrits":1505,"votants":865,"participation":57.48,"status":"elu","bord":"indecis","candidats":[{"nom":"Un territoire, des valeurs, un avenir ensemble","parti":"Un territoire, des valeurs, un avenir ensemble","bord":"Divers","score":100.0,"color":"var(--div)"}]},{"code":"46064","nom":"Catus","inscrits":691,"votants":400,"participation":57.89,"status":"elu","bord":"indecis","candidats":[{"nom":"Continuons ensemble","parti":"Continuons ensemble","bord":"Divers","score":100.0,"color":"var(--div)"}]},{"code":"46065","nom":"Cavagnac","inscrits":395,"votants":292,"participation":73.92,"status":"elu","bord":"indecis","candidats":[{"nom":"CAVAGNAC, NOTRE VILLAGE, NOTRE AVENIR","parti":"CAVAGNAC, NOTRE VILLAGE, NOTRE AVENIR","bord":"Divers","score":100.0,"color":"var(--div)"}]},{"code":"46066","nom":"Cazals","inscrits":482,"votants":381,"participation":79.05,"status":"elu","bord":"indecis","candidats":[{"nom":"AVANÇONS ENSEMBLE POUR CAZALS","parti":"AVANÇONS ENSEMBLE POUR CAZALS","bord":"Divers","score":52.67,"color":"var(--div)"},{"nom":"CAZALS L'OUVERTURE","parti":"CAZALS L'OUVERTURE","bord":"Divers","score":47.33,"color":"var(--div)"}]},{"code":"46068","nom":"Cénevières","inscrits":167,"votants":114,"participation":68.26,"status":"elu","bord":"indecis","candidats":[{"nom":"Cénevières 2026","parti":"Cénevières 2026","bord":"Divers","score":100.0,"color":"var(--div)"}]},{"code":"46069","nom":"Cézac","inscrits":174,"votants":107,"participation":61.49,"status":"elu","bord":"indecis","candidats":[{"nom":"Bien vivre ensemble à Cézac","parti":"Bien vivre ensemble à Cézac","bord":"Divers","score":100.0,"color":"var(--div)"}]},{"code":"46070","nom":"Cieurac","inscrits":546,"votants":437,"participation":80.04,"status":"elu","bord":"indecis","candidats":[{"nom":"Cieurac, notre village, une équipe","parti":"Cieurac, notre village, une équipe","bord":"Divers","score":65.5,"color":"var(--div)"},{"nom":"CIEURAC UNI(E)S POUR NOTRE COMMUNE DANS UN NOUVEL ELAN","parti":"CIEURAC UNI(E)S POUR NOTRE COMMUNE DANS UN NOUVEL ELAN","bord":"Divers","score":34.5,"color":"var(--div)"}]},{"code":"46072","nom":"Concorès","inscrits":293,"votants":215,"participation":73.38,"status":"elu","bord":"indecis","candidats":[{"nom":"CONCORÈS, VILLAGE VIVANT ET SOLIDAIRE","parti":"CONCORÈS, VILLAGE VIVANT ET SOLIDAIRE","bord":"Divers","score":100.0,"color":"var(--div)"}]},{"code":"46073","nom":"Concots","inscrits":401,"votants":320,"participation":79.8,"status":"elu","bord":"indecis","candidats":[{"nom":"Concots au coeur","parti":"Concots au coeur","bord":"Divers","score":56.86,"color":"var(--div)"},{"nom":"Concots en action","parti":"Concots en action","bord":"Divers","score":43.14,"color":"var(--div)"}]},{"code":"46074","nom":"Condat","inscrits":323,"votants":221,"participation":68.42,"status":"elu","bord":"indecis","candidats":[{"nom":"CONDAT TOUS ENSEMBLE","parti":"CONDAT TOUS ENSEMBLE","bord":"Divers","score":100.0,"color":"var(--div)"}]},{"code":"46075","nom":"Corn","inscrits":220,"votants":185,"participation":84.09,"status":"elu","bord":"indecis","candidats":[{"nom":"CORN AU SERVICE DE CHACUN ET DANS L'INTERET DE TOUS","parti":"CORN AU SERVICE DE CHACUN ET DANS L'INTERET DE TOUS","bord":"Divers","score":61.2,"color":"var(--div)"},{"nom":"AUTRE VOIX, AUTRE DYNAMIQUE","parti":"AUTRE VOIX, AUTRE DYNAMIQUE","bord":"Divers","score":38.8,"color":"var(--div)"}]},{"code":"46076","nom":"Cornac","inscrits":295,"votants":190,"participation":64.41,"status":"elu","bord":"indecis","candidats":[{"nom":"CORNAC POUR TOUS","parti":"CORNAC POUR TOUS","bord":"Divers","score":100.0,"color":"var(--div)"}]},{"code":"46078","nom":"Couzou","inscrits":105,"votants":98,"participation":93.33,"status":"2t","bord":"indecis","candidats":[{"nom":"AVEC SANDRINE POUR COUZOU","parti":"AVEC SANDRINE POUR COUZOU","bord":"Divers","score":42.11,"color":"var(--div)"},{"nom":"POUR COUZOU, AVEC VOUS","parti":"POUR COUZOU, AVEC VOUS","bord":"Divers","score":32.63,"color":"var(--div)"},{"nom":"VIVRE A COUZOU","parti":"VIVRE A COUZOU","bord":"Divers","score":25.26,"color":"var(--div)"}]},{"code":"46079","nom":"Cras","inscrits":92,"votants":69,"participation":75.0,"status":"elu","bord":"indecis","candidats":[{"nom":"LISTE POUR CRAS","parti":"LISTE POUR CRAS","bord":"Divers","score":100.0,"color":"var(--div)"}]},{"code":"46080","nom":"Crayssac","inscrits":673,"votants":507,"participation":75.33,"status":"elu","bord":"indecis","candidats":[{"nom":"Ensemble, notre village, notre avenir","parti":"Ensemble, notre village, notre avenir","bord":"Divers","score":68.51,"color":"var(--div)"},{"nom":"Osons Crayssac en commun","parti":"Osons Crayssac en commun","bord":"Divers","score":31.49,"color":"var(--div)"}]},{"code":"46081","nom":"Crégols","inscrits":74,"votants":42,"participation":56.76,"status":"elu","bord":"indecis","candidats":[{"nom":"Crégols","parti":"Crégols","bord":"Divers","score":100.0,"color":"var(--div)"}]},{"code":"46082","nom":"Cremps","inscrits":330,"votants":275,"participation":83.33,"status":"elu","bord":"indecis","candidats":[{"nom":"Cremps, ma commune en commun","parti":"Cremps, ma commune en commun","bord":"Divers","score":58.27,"color":"var(--div)"},{"nom":"Bien vivre à Cremps","parti":"Bien vivre à Cremps","bord":"Divers","score":41.73,"color":"var(--div)"}]},{"code":"46083","nom":"Cressensac-Sarrazac","inscrits":1004,"votants":750,"participation":74.7,"status":"elu","bord":"indecis","candidats":[{"nom":"POUR UNE DYNAMIQUE COMMUNE","parti":"POUR UNE DYNAMIQUE COMMUNE","bord":"Divers","score":54.21,"color":"var(--div)"},{"nom":"CRESSENSAC-SARRAZAC UNIS DANS UN NOUVEL ÉLAN","parti":"CRESSENSAC-SARRAZAC UNIS DANS UN NOUVEL ÉLAN","bord":"Divers","score":45.79,"color":"var(--div)"}]},{"code":"46084","nom":"Creysse","inscrits":268,"votants":221,"participation":82.46,"status":"elu","bord":"indecis","candidats":[{"nom":"AGIR AVEC VOUS POUR CREYSSE","parti":"AGIR AVEC VOUS POUR CREYSSE","bord":"Divers","score":57.53,"color":"var(--div)"},{"nom":"CHRISTOPHE MOREL","parti":"CHRISTOPHE MOREL","bord":"Divers","score":42.47,"color":"var(--div)"}]},{"code":"46085","nom":"Cuzac","inscrits":171,"votants":113,"participation":66.08,"status":"elu","bord":"indecis","candidats":[{"nom":"DEMAIN NOTRE VILLAGE CUZAC","parti":"DEMAIN NOTRE VILLAGE CUZAC","bord":"Divers","score":100.0,"color":"var(--div)"}]},{"code":"46086","nom":"Cuzance","inscrits":511,"votants":361,"participation":70.65,"status":"elu","bord":"indecis","candidats":[{"nom":"UNION COMMUNALE POUR LE PROGRÉS ET LA LIBÉRTÉ","parti":"UNION COMMUNALE POUR LE PROGRÉS ET LA LIBÉRTÉ","bord":"Divers","score":100.0,"color":"var(--div)"}]},{"code":"46087","nom":"Dégagnac","inscrits":576,"votants":435,"participation":75.52,"status":"elu","bord":"indecis","candidats":[{"nom":"ENSEMBLE CONTINUONS À FAIRE GRANDIR DÉGAGNAC","parti":"ENSEMBLE CONTINUONS À FAIRE GRANDIR DÉGAGNAC","bord":"Divers","score":78.18,"color":"var(--div)"},{"nom":"AGIR POUR DÉGAGNAC","parti":"AGIR POUR DÉGAGNAC","bord":"Divers","score":21.82,"color":"var(--div)"}]},{"code":"46088","nom":"Douelle","inscrits":709,"votants":456,"participation":64.32,"status":"elu","bord":"indecis","candidats":[{"nom":"DOUELLE DEMAIN","parti":"DOUELLE DEMAIN","bord":"Divers","score":100.0,"color":"var(--div)"}]},{"code":"46089","nom":"Duravel","inscrits":766,"votants":410,"participation":53.52,"status":"elu","bord":"indecis","candidats":[{"nom":"Agir ensemble pour Duravel","parti":"Agir ensemble pour Duravel","bord":"Divers","score":100.0,"color":"var(--div)"}]},{"code":"46090","nom":"Durbans","inscrits":136,"votants":92,"participation":67.65,"status":"elu","bord":"indecis","candidats":[{"nom":"LISTE D'UNION ET DE DEFENSE DES INTERETS COMMUNAUX","parti":"LISTE D'UNION ET DE DEFENSE DES INTERETS COMMUNAUX","bord":"Divers","score":100.0,"color":"var(--div)"}]},{"code":"46091","nom":"Escamps","inscrits":198,"votants":163,"participation":82.32,"status":"elu","bord":"indecis","candidats":[{"nom":"Un héritage à transmettre, un futur à bâtir","parti":"Un héritage à transmettre, un futur à bâtir","bord":"Divers","score":60.51,"color":"var(--div)"},{"nom":"Ensemble pour Escamps","parti":"Ensemble pour Escamps","bord":"Divers","score":39.49,"color":"var(--div)"}]},{"code":"46092","nom":"Esclauzels","inscrits":224,"votants":130,"participation":58.04,"status":"elu","bord":"indecis","candidats":[{"nom":"Esclauzels, notre commune","parti":"Esclauzels, notre commune","bord":"Divers","score":100.0,"color":"var(--div)"}]},{"code":"46093","nom":"Espagnac-Sainte-Eulalie","inscrits":88,"votants":61,"participation":69.32,"status":"elu","bord":"indecis","candidats":[{"nom":"ESPAGNAC-SAINTE-EULALIE","parti":"ESPAGNAC-SAINTE-EULALIE","bord":"Divers","score":100.0,"color":"var(--div)"}]},{"code":"46094","nom":"Espédaillac","inscrits":272,"votants":188,"participation":69.12,"status":"elu","bord":"indecis","candidats":[{"nom":"ENSEMBLE POUR ESPEDAILLAC","parti":"ENSEMBLE POUR ESPEDAILLAC","bord":"Divers","score":100.0,"color":"var(--div)"}]},{"code":"46095","nom":"Espère","inscrits":755,"votants":405,"participation":53.64,"status":"elu","bord":"indecis","candidats":[{"nom":"ESPERE NOTRE AVENIR COMMUN","parti":"ESPERE NOTRE AVENIR COMMUN","bord":"Divers","score":100.0,"color":"var(--div)"}]},{"code":"46096","nom":"Espeyroux","inscrits":95,"votants":65,"participation":68.42,"status":"elu","bord":"indecis","candidats":[{"nom":"ESPEYROUX AVEC VOUS POUR VOUS","parti":"ESPEYROUX AVEC VOUS POUR VOUS","bord":"Divers","score":100.0,"color":"var(--div)"}]},{"code":"46097","nom":"Estal","inscrits":97,"votants":61,"participation":62.89,"status":"elu","bord":"indecis","candidats":[{"nom":"ENGAGES POUR ESTAL","parti":"ENGAGES POUR ESTAL","bord":"Divers","score":100.0,"color":"var(--div)"}]},{"code":"46098","nom":"Fajoles","inscrits":278,"votants":188,"participation":67.63,"status":"elu","bord":"indecis","candidats":[{"nom":"AGIR ENSEMBLE POUR FAJOLES","parti":"AGIR ENSEMBLE POUR FAJOLES","bord":"Divers","score":100.0,"color":"var(--div)"}]},{"code":"46100","nom":"Faycelles","inscrits":614,"votants":432,"participation":70.36,"status":"elu","bord":"indecis","candidats":[{"nom":"ENSEMBLE POUR FAYCELLES","parti":"ENSEMBLE POUR FAYCELLES","bord":"Divers","score":100.0,"color":"var(--div)"}]},{"code":"46101","nom":"Felzins","inscrits":389,"votants":274,"participation":70.44,"status":"elu","bord":"indecis","candidats":[{"nom":"Felzins, ensemble on agit","parti":"Felzins, ensemble on agit","bord":"Divers","score":100.0,"color":"var(--div)"}]},{"code":"46102","nom":"Figeac","inscrits":7053,"votants":4294,"participation":60.88,"status":"2t","bord":"indecis","candidats":[{"nom":"FIGEAC AUTREMENT","parti":"FIGEAC AUTREMENT","bord":"Divers","score":49.46,"color":"var(--div)"},{"nom":"FIGEAC ENSEMBLE","parti":"FIGEAC ENSEMBLE","bord":"Gauche","score":34.56,"color":"var(--ps)"},{"nom":"FIGEAC CITOYENNE ECOLOGIQUE SOCIALE","parti":"FIGEAC CITOYENNE ECOLOGIQUE SOCIALE","bord":"Gauche","score":15.99,"color":"var(--ps)"}]},{"code":"46103","nom":"Saint-Paul-Flaugnac","inscrits":866,"votants":541,"participation":62.47,"status":"elu","bord":"indecis","candidats":[{"nom":"POURSUIVRE ENSEMBLE","parti":"POURSUIVRE ENSEMBLE","bord":"Divers","score":100.0,"color":"var(--div)"}]},{"code":"46104","nom":"Flaujac-Gare","inscrits":89,"votants":55,"participation":61.8,"status":"elu","bord":"indecis","candidats":[{"nom":"ELAN de Flaujac gare","parti":"ELAN de Flaujac gare","bord":"Divers","score":100.0,"color":"var(--div)"}]},{"code":"46105","nom":"Flaujac-Poujols","inscrits":686,"votants":441,"participation":64.29,"status":"elu","bord":"indecis","candidats":[{"nom":"Flaujac-Poujols ensemble pour demain","parti":"Flaujac-Poujols ensemble pour demain","bord":"Divers","score":100.0,"color":"var(--div)"}]},{"code":"46106","nom":"Floirac","inscrits":242,"votants":172,"participation":71.07,"status":"elu","bord":"indecis","candidats":[{"nom":"FLOIRAC NATURELLEMENT !","parti":"FLOIRAC NATURELLEMENT !","bord":"Divers","score":100.0,"color":"var(--div)"}]},{"code":"46107","nom":"Floressas","inscrits":154,"votants":100,"participation":64.94,"status":"elu","bord":"indecis","candidats":[{"nom":"Floressas, village vivant, un futur à bâtir","parti":"Floressas, village vivant, un futur à bâtir","bord":"Divers","score":100.0,"color":"var(--div)"}]},{"code":"46108","nom":"Fons","inscrits":374,"votants":253,"participation":67.65,"status":"elu","bord":"indecis","candidats":[{"nom":"CONTINUONS ENSEMBLE POUR NOTRE VILLAGE","parti":"CONTINUONS ENSEMBLE POUR NOTRE VILLAGE","bord":"Divers","score":100.0,"color":"var(--div)"}]},{"code":"46109","nom":"Fontanes","inscrits":437,"votants":359,"participation":82.15,"status":"elu","bord":"indecis","candidats":[{"nom":"Vivons notre village","parti":"Vivons notre village","bord":"Divers","score":53.82,"color":"var(--div)"},{"nom":"Fontanes Saint-Cevet Autrement","parti":"Fontanes Saint-Cevet Autrement","bord":"Divers","score":46.18,"color":"var(--div)"}]},{"code":"46111","nom":"Fourmagnac","inscrits":164,"votants":102,"participation":62.2,"status":"elu","bord":"indecis","candidats":[{"nom":"LISTE D'UNION ET DE DEFENSE DES INTERETS COMMUNAUX","parti":"LISTE D'UNION ET DE DEFENSE DES INTERETS COMMUNAUX","bord":"Divers","score":100.0,"color":"var(--div)"}]},{"code":"46112","nom":"Francoulès","inscrits":222,"votants":175,"participation":78.83,"status":"elu","bord":"indecis","candidats":[{"nom":"Un nouvel élan pour Francoulès","parti":"Un nouvel élan pour Francoulès","bord":"Divers","score":55.49,"color":"var(--div)"},{"nom":"Une équipe qui nous rassemble","parti":"Une équipe qui nous rassemble","bord":"Divers","score":44.51,"color":"var(--div)"}]},{"code":"46113","nom":"Frayssinet","inscrits":295,"votants":260,"participation":88.14,"status":"elu","bord":"indecis","candidats":[{"nom":"IMAGINONS DEMAIN AGISSONS MAINTENANT","parti":"IMAGINONS DEMAIN AGISSONS MAINTENANT","bord":"Divers","score":65.6,"color":"var(--div)"},{"nom":"FRAYSSINET SOLIDAIRE","parti":"FRAYSSINET SOLIDAIRE","bord":"Divers","score":34.4,"color":"var(--div)"}]},{"code":"46114","nom":"Frayssinet-le-Gélat","inscrits":327,"votants":202,"participation":61.77,"status":"elu","bord":"indecis","candidats":[{"nom":"FRAYSSINET-LE-GELAT ENSEMBLE 2026","parti":"FRAYSSINET-LE-GELAT ENSEMBLE 2026","bord":"Divers","score":100.0,"color":"var(--div)"}]},{"code":"46115","nom":"Frayssinhes","inscrits":148,"votants":104,"participation":70.27,"status":"elu","bord":"indecis","candidats":[{"nom":"ENSEMBLE POUR FRAYSSINHES","parti":"ENSEMBLE POUR FRAYSSINHES","bord":"Divers","score":100.0,"color":"var(--div)"}]},{"code":"46116","nom":"Frontenac","inscrits":65,"votants":48,"participation":73.85,"status":"elu","bord":"indecis","candidats":[{"nom":"FRONTENAC","parti":"FRONTENAC","bord":"Divers","score":100.0,"color":"var(--div)"}]},{"code":"46117","nom":"Gagnac-sur-Cère","inscrits":567,"votants":387,"participation":68.25,"status":"elu","bord":"indecis","candidats":[{"nom":"REDONNER A GAGNAC L'ÂME D'UN TERRITOIRE","parti":"REDONNER A GAGNAC L'ÂME D'UN TERRITOIRE","bord":"Divers","score":100.0,"color":"var(--div)"}]},{"code":"46118","nom":"Gignac","inscrits":577,"votants":383,"participation":66.38,"status":"elu","bord":"indecis","candidats":[{"nom":"TOUS POUR GIGNAC","parti":"TOUS POUR GIGNAC","bord":"Divers","score":100.0,"color":"var(--div)"}]},{"code":"46119","nom":"Gigouzac","inscrits":207,"votants":154,"participation":74.4,"status":"elu","bord":"indecis","candidats":[{"nom":"Vivre Gigouzac","parti":"Vivre Gigouzac","bord":"Divers","score":100.0,"color":"var(--div)"}]},{"code":"46120","nom":"Gindou","inscrits":260,"votants":192,"participation":73.85,"status":"elu","bord":"indecis","candidats":[{"nom":"ENSEMBLE POUR GINDOU","parti":"ENSEMBLE POUR GINDOU","bord":"Divers","score":100.0,"color":"var(--div)"}]},{"code":"46121","nom":"Ginouillac","inscrits":148,"votants":110,"participation":74.32,"status":"elu","bord":"indecis","candidats":[{"nom":"AGIR POUR L'AVENIR","parti":"AGIR POUR L'AVENIR","bord":"Divers","score":100.0,"color":"var(--div)"}]},{"code":"46122","nom":"Gintrac","inscrits":92,"votants":64,"participation":69.57,"status":"elu","bord":"indecis","candidats":[{"nom":"Liste d'Union Communale","parti":"Liste d'Union Communale","bord":"Divers","score":100.0,"color":"var(--div)"}]},{"code":"46123","nom":"Girac","inscrits":293,"votants":183,"participation":62.46,"status":"elu","bord":"indecis","candidats":[{"nom":"ENSEMBLE A GIRAC","parti":"ENSEMBLE A GIRAC","bord":"Divers","score":100.0,"color":"var(--div)"}]},{"code":"46124","nom":"Glanes","inscrits":225,"votants":168,"participation":74.67,"status":"elu","bord":"indecis","candidats":[{"nom":"UN AVENIR COMMUN POUR GLANES","parti":"UN AVENIR COMMUN POUR GLANES","bord":"Divers","score":100.0,"color":"var(--div)"}]},{"code":"46125","nom":"Gorses","inscrits":297,"votants":229,"participation":77.1,"status":"elu","bord":"indecis","candidats":[{"nom":"ENSEMBLE POUR GORSES","parti":"ENSEMBLE POUR GORSES","bord":"Divers","score":63.96,"color":"var(--div)"},{"nom":"IMAGINONS DEMAIN / AGISSONS MAINTENANT","parti":"IMAGINONS DEMAIN / AGISSONS MAINTENANT","bord":"Divers","score":36.04,"color":"var(--div)"}]},{"code":"46126","nom":"Goujounac","inscrits":151,"votants":120,"participation":79.47,"status":"elu","bord":"indecis","candidats":[{"nom":"AGIR ENSEMBLE POUR GOUJOUNAC","parti":"AGIR ENSEMBLE POUR GOUJOUNAC","bord":"Divers","score":100.0,"color":"var(--div)"}]},{"code":"46127","nom":"Gourdon","inscrits":3483,"votants":2237,"participation":64.23,"status":"elu","bord":"indecis","candidats":[{"nom":"GOURDON AVANCE","parti":"GOURDON AVANCE","bord":"Divers","score":54.68,"color":"var(--div)"},{"nom":"UN NOUVEL ÉLAN POUR GOURDON","parti":"UN NOUVEL ÉLAN POUR GOURDON","bord":"Divers","score":45.32,"color":"var(--div)"}]},{"code":"46128","nom":"Gramat","inscrits":2706,"votants":1625,"participation":60.05,"status":"elu","bord":"indecis","candidats":[{"nom":"GRAMAT, NOTRE FORCE, VOTRE VOIX !","parti":"GRAMAT, NOTRE FORCE, VOTRE VOIX !","bord":"Divers","score":52.19,"color":"var(--div)"},{"nom":"UN NOUVEL ELAN POUR GRAMAT","parti":"UN NOUVEL ELAN POUR GRAMAT","bord":"Divers","score":41.1,"color":"var(--div)"},{"nom":"VIVRE BIEN À GRAMAT","parti":"VIVRE BIEN À GRAMAT","bord":"Divers","score":6.71,"color":"var(--div)"}]},{"code":"46129","nom":"Gréalou","inscrits":269,"votants":186,"participation":69.14,"status":"elu","bord":"indecis","candidats":[{"nom":"ENSEMBLE POUR UN BEL AVENIR","parti":"ENSEMBLE POUR UN BEL AVENIR","bord":"Divers","score":100.0,"color":"var(--div)"}]},{"code":"46130","nom":"Grézels","inscrits":187,"votants":137,"participation":73.26,"status":"elu","bord":"indecis","candidats":[{"nom":"Ensemble pour Grézels","parti":"Ensemble pour Grézels","bord":"Divers","score":100.0,"color":"var(--div)"}]},{"code":"46131","nom":"Grèzes","inscrits":155,"votants":83,"participation":53.55,"status":"elu","bord":"indecis","candidats":[{"nom":"GREZES DANS LA CONTINUITE ET LA CONFIANCE","parti":"GREZES DANS LA CONTINUITE ET LA CONFIANCE","bord":"Divers","score":100.0,"color":"var(--div)"}]},{"code":"46132","nom":"Issendolus","inscrits":454,"votants":293,"participation":64.54,"status":"elu","bord":"indecis","candidats":[{"nom":"ENSEMBLE POUR ISSENDOLUS","parti":"ENSEMBLE POUR ISSENDOLUS","bord":"Divers","score":100.0,"color":"var(--div)"}]},{"code":"46133","nom":"Issepts","inscrits":219,"votants":180,"participation":82.19,"status":"elu","bord":"indecis","candidats":[{"nom":"AGIR ENSEMBLE POUR ISSEPTS","parti":"AGIR ENSEMBLE POUR ISSEPTS","bord":"Divers","score":61.31,"color":"var(--div)"},{"nom":"UN VILLAGE QUI SE RASSEMBLE","parti":"UN VILLAGE QUI SE RASSEMBLE","bord":"Divers","score":38.69,"color":"var(--div)"}]},{"code":"46134","nom":"Les Junies","inscrits":254,"votants":221,"participation":87.01,"status":"elu","bord":"indecis","candidats":[{"nom":"Les Junies en mouvement !","parti":"Les Junies en mouvement !","bord":"Divers","score":65.53,"color":"var(--div)"},{"nom":"Agissons pour Les Junies","parti":"Agissons pour Les Junies","bord":"Divers","score":34.47,"color":"var(--div)"}]},{"code":"46135","nom":"Labastide-du-Haut-Mont","inscrits":52,"votants":36,"participation":69.23,"status":"elu","bord":"indecis","candidats":[{"nom":"SOLIDAIRES POUR LABASTIDE","parti":"SOLIDAIRES POUR LABASTIDE","bord":"Divers","score":100.0,"color":"var(--div)"}]},{"code":"46136","nom":"Labastide-du-Vert","inscrits":265,"votants":208,"participation":78.49,"status":"elu","bord":"indecis","candidats":[{"nom":"Faire village","parti":"Faire village","bord":"Divers","score":55.72,"color":"var(--div)"},{"nom":"Ensemble pour Labastide-du-Vert","parti":"Ensemble pour Labastide-du-Vert","bord":"Divers","score":44.28,"color":"var(--div)"}]},{"code":"46137","nom":"Labastide-Marnhac","inscrits":1108,"votants":573,"participation":51.71,"status":"elu","bord":"indecis","candidats":[{"nom":"Agir ensemble pour l'avenir","parti":"Agir ensemble pour l'avenir","bord":"Divers","score":100.0,"color":"var(--div)"}]},{"code":"46138","nom":"Coeur de Causse","inscrits":832,"votants":676,"participation":81.25,"status":"elu","bord":"indecis","candidats":[{"nom":"ENSEMBLE POUR NOS VILLAGES","parti":"ENSEMBLE POUR NOS VILLAGES","bord":"Divers","score":53.57,"color":"var(--div)"},{"nom":"TOUS UNIS POUR COEUR DE CAUSSE","parti":"TOUS UNIS POUR COEUR DE CAUSSE","bord":"Divers","score":46.43,"color":"var(--div)"}]},{"code":"46139","nom":"Labathude","inscrits":177,"votants":128,"participation":72.32,"status":"elu","bord":"indecis","candidats":[{"nom":"LABATHUDE, NOTRE VILLAGE, NOS VIES","parti":"LABATHUDE, NOTRE VILLAGE, NOS VIES","bord":"Divers","score":100.0,"color":"var(--div)"}]},{"code":"46140","nom":"Laburgade","inscrits":340,"votants":216,"participation":63.53,"status":"elu","bord":"indecis","candidats":[{"nom":"Ensemble pour Laburgade","parti":"Ensemble pour Laburgade","bord":"Divers","score":100.0,"color":"var(--div)"}]},{"code":"46142","nom":"Lacapelle-Cabanac","inscrits":152,"votants":100,"participation":65.79,"status":"elu","bord":"indecis","candidats":[{"nom":"Continuons ensemble pour Lacapelle-Cabanac","parti":"Continuons ensemble pour Lacapelle-Cabanac","bord":"Divers","score":100.0,"color":"var(--div)"}]},{"code":"46143","nom":"Lacapelle-Marival","inscrits":886,"votants":515,"participation":58.13,"status":"elu","bord":"indecis","candidats":[{"nom":"LACAPELLE AVENIR","parti":"LACAPELLE AVENIR","bord":"Divers","score":100.0,"color":"var(--div)"}]},{"code":"46144","nom":"Lacave","inscrits":232,"votants":157,"participation":67.67,"status":"elu","bord":"indecis","candidats":[{"nom":"LACAVE, VOTRE VILLAGE","parti":"LACAVE, VOTRE VILLAGE","bord":"Divers","score":100.0,"color":"var(--div)"}]},{"code":"46145","nom":"Lachapelle-Auzac","inscrits":662,"votants":391,"participation":59.06,"status":"elu","bord":"indecis","candidats":[{"nom":"S'ASSOCIER POUR L'AVENIR","parti":"S'ASSOCIER POUR L'AVENIR","bord":"Divers","score":100.0,"color":"var(--div)"}]},{"code":"46146","nom":"Ladirat","inscrits":89,"votants":66,"participation":74.16,"status":"elu","bord":"indecis","candidats":[{"nom":"ENSEMBLE POUR LADIRAT","parti":"ENSEMBLE POUR LADIRAT","bord":"Divers","score":100.0,"color":"var(--div)"}]},{"code":"46147","nom":"Lagardelle","inscrits":105,"votants":79,"participation":75.24,"status":"elu","bord":"indecis","candidats":[{"nom":"Lagardelle demain","parti":"Lagardelle demain","bord":"Divers","score":100.0,"color":"var(--div)"}]},{"code":"46148","nom":"Lalbenque","inscrits":1568,"votants":1192,"participation":76.02,"status":"elu","bord":"indecis","candidats":[{"nom":"LALBENQUE ENERGIE COMMUNE","parti":"LALBENQUE ENERGIE COMMUNE","bord":"Divers","score":62.4,"color":"var(--div)"},{"nom":"Lalbenque Ensemble","parti":"Lalbenque Ensemble","bord":"Divers","score":37.6,"color":"var(--div)"}]},{"code":"46149","nom":"Lamagdelaine","inscrits":664,"votants":481,"participation":72.44,"status":"elu","bord":"indecis","candidats":[{"nom":"Bien vivre ensemble à Lamagdelaine","parti":"Bien vivre ensemble à Lamagdelaine","bord":"Divers","score":58.51,"color":"var(--div)"},{"nom":"Lamagdeleine pour vous, avec vous","parti":"Lamagdeleine pour vous, avec vous","bord":"Divers","score":41.49,"color":"var(--div)"}]},{"code":"46151","nom":"Lamothe-Cassel","inscrits":106,"votants":72,"participation":67.92,"status":"elu","bord":"indecis","candidats":[{"nom":"LAMOTHE-CASSEL, NOTRE VILLAGE, NOTRE AVENIR","parti":"LAMOTHE-CASSEL, NOTRE VILLAGE, NOTRE AVENIR","bord":"Divers","score":100.0,"color":"var(--div)"}]},{"code":"46152","nom":"Lamothe-Fénelon","inscrits":280,"votants":226,"participation":80.71,"status":"elu","bord":"indecis","candidats":[{"nom":"LAMOTHE FENELON, LE TRAIT D'UNION DE NOTRE QUOTIDIEN","parti":"LAMOTHE FENELON, LE TRAIT D'UNION DE NOTRE QUOTIDIEN","bord":"Divers","score":61.86,"color":"var(--div)"},{"nom":"LISTE D'UNION COMMUNALE","parti":"LISTE D'UNION COMMUNALE","bord":"Divers","score":38.14,"color":"var(--div)"}]},{"code":"46153","nom":"Lanzac","inscrits":525,"votants":352,"participation":67.05,"status":"elu","bord":"indecis","candidats":[{"nom":"POUR VOUS, POUR LANZAC","parti":"POUR VOUS, POUR LANZAC","bord":"Divers","score":100.0,"color":"var(--div)"}]},{"code":"46154","nom":"Laramière","inscrits":277,"votants":171,"participation":61.73,"status":"elu","bord":"indecis","candidats":[{"nom":"Ensemble pour Laramière","parti":"Ensemble pour Laramière","bord":"Divers","score":100.0,"color":"var(--div)"}]},{"code":"46155","nom":"Larnagol","inscrits":116,"votants":79,"participation":68.1,"status":"elu","bord":"indecis","candidats":[{"nom":"LARNAGOL SEUZAC UNIS DYNAMIQUE COMMUNE","parti":"LARNAGOL SEUZAC UNIS DYNAMIQUE COMMUNE","bord":"Divers","score":100.0,"color":"var(--div)"}]},{"code":"46156","nom":"Bellefont-La Rauze","inscrits":994,"votants":707,"participation":71.13,"status":"elu","bord":"indecis","candidats":[{"nom":"Bellefont-La Rauze, avec vous, préparons demain !","parti":"Bellefont-La Rauze, avec vous, préparons demain !","bord":"Divers","score":65.74,"color":"var(--div)"},{"nom":"Bellefont-La Rauze: Notre commune, aujourd'hui pour demain","parti":"Bellefont-La Rauze: Notre commune, aujourd'hui pour demain","bord":"Divers","score":34.26,"color":"var(--div)"}]},{"code":"46157","nom":"Larroque-Toirac","inscrits":128,"votants":93,"participation":72.66,"status":"elu","bord":"indecis","candidats":[{"nom":"ENSEMBLE POUR LARROQUE TOIRAC","parti":"ENSEMBLE POUR LARROQUE TOIRAC","bord":"Divers","score":100.0,"color":"var(--div)"}]},{"code":"46159","nom":"Latouille-Lentillac","inscrits":211,"votants":148,"participation":70.14,"status":"elu","bord":"indecis","candidats":[{"nom":"VIVRE ET AGIR ENSEMBLE POUR LATOUILLE-LENTILLAC","parti":"VIVRE ET AGIR ENSEMBLE POUR LATOUILLE-LENTILLAC","bord":"Divers","score":100.0,"color":"var(--div)"}]},{"code":"46160","nom":"Latronquière","inscrits":331,"votants":222,"participation":67.07,"status":"elu","bord":"indecis","candidats":[{"nom":"AGIR ET VIVRE A LATRONQUIERE","parti":"AGIR ET VIVRE A LATRONQUIERE","bord":"Divers","score":100.0,"color":"var(--div)"}]},{"code":"46161","nom":"Lauresses","inscrits":232,"votants":143,"participation":61.64,"status":"elu","bord":"indecis","candidats":[{"nom":"AGIR ENSEMBLE POUR LAURESSES","parti":"AGIR ENSEMBLE POUR LAURESSES","bord":"Divers","score":100.0,"color":"var(--div)"}]},{"code":"46162","nom":"Lauzès","inscrits":184,"votants":125,"participation":67.93,"status":"elu","bord":"indecis","candidats":[{"nom":"VIVRE À LAUZÈS","parti":"VIVRE À LAUZÈS","bord":"Divers","score":100.0,"color":"var(--div)"}]},{"code":"46163","nom":"Laval-de-Cère","inscrits":249,"votants":159,"participation":63.86,"status":"elu","bord":"indecis","candidats":[{"nom":"LAVAL D'AVENIR","parti":"LAVAL D'AVENIR","bord":"Divers","score":100.0,"color":"var(--div)"}]},{"code":"46164","nom":"Lavercantière","inscrits":218,"votants":142,"participation":65.14,"status":"elu","bord":"indecis","candidats":[{"nom":"POUR UNE RURALITÉ PARTAGÉE","parti":"POUR UNE RURALITÉ PARTAGÉE","bord":"Divers","score":100.0,"color":"var(--div)"}]},{"code":"46165","nom":"Lavergne","inscrits":361,"votants":260,"participation":72.02,"status":"elu","bord":"indecis","candidats":[{"nom":"AGIR ENSEMBLE POUR LAVERGNE","parti":"AGIR ENSEMBLE POUR LAVERGNE","bord":"Divers","score":100.0,"color":"var(--div)"}]},{"code":"46167","nom":"Lentillac-du-Causse","inscrits":91,"votants":66,"participation":72.53,"status":"elu","bord":"indecis","candidats":[{"nom":"LENTILLAC TERRE D'ÉCHANGES DIVERS ET OUVERT POUR UN VILLAGE UNI","parti":"LENTILLAC TERRE D'ÉCHANGES DIVERS ET OUVERT POUR UN VILLAGE UNI","bord":"Divers","score":100.0,"color":"var(--div)"}]},{"code":"46168","nom":"Lentillac-Saint-Blaise","inscrits":161,"votants":110,"participation":68.32,"status":"elu","bord":"indecis","candidats":[{"nom":"ENSEMBLE POUR LENTILLAC SAINT BLAISE","parti":"ENSEMBLE POUR LENTILLAC SAINT BLAISE","bord":"Divers","score":100.0,"color":"var(--div)"}]},{"code":"46169","nom":"Léobard","inscrits":206,"votants":175,"participation":84.95,"status":"elu","bord":"indecis","candidats":[{"nom":"ENSEMBLE POUR L'AVENIR DE NOTRE COMMUNE","parti":"ENSEMBLE POUR L'AVENIR DE NOTRE COMMUNE","bord":"Divers","score":52.69,"color":"var(--div)"},{"nom":"EN AVANT LÉOBARD","parti":"EN AVANT LÉOBARD","bord":"Divers","score":47.31,"color":"var(--div)"}]},{"code":"46170","nom":"Leyme","inscrits":600,"votants":404,"participation":67.33,"status":"elu","bord":"indecis","candidats":[{"nom":"PRESERVER NOTRE VILLAGE, PREPARER SON AVENIR","parti":"PRESERVER NOTRE VILLAGE, PREPARER SON AVENIR","bord":"Divers","score":100.0,"color":"var(--div)"}]},{"code":"46171","nom":"Lherm","inscrits":185,"votants":122,"participation":65.95,"status":"elu","bord":"indecis","candidats":[{"nom":"La confiance ancrée dans une ruralité et un patrimoine en mouvement","parti":"La confiance ancrée dans une ruralité et un patrimoine en mouvement","bord":"Divers","score":100.0,"color":"var(--div)"}]},{"code":"46172","nom":"Pern-Lhospitalet","inscrits":736,"votants":412,"participation":55.98,"status":"elu","bord":"indecis","candidats":[{"nom":"Agir pour Pern-Lhospitalet","parti":"Agir pour Pern-Lhospitalet","bord":"Divers","score":100.0,"color":"var(--div)"}]},{"code":"46173","nom":"Limogne-en-Quercy","inscrits":643,"votants":371,"participation":57.7,"status":"elu","bord":"indecis","candidats":[{"nom":"Limogne rassemble, vivant aujourd'hui, ambitieux pour demain","parti":"Limogne rassemble, vivant aujourd'hui, ambitieux pour demain","bord":"Divers","score":100.0,"color":"var(--div)"}]},{"code":"46174","nom":"Linac","inscrits":190,"votants":132,"participation":69.47,"status":"elu","bord":"indecis","candidats":[{"nom":"UNION POUR LA DEFENSE DES INTERETS DE LINAC","parti":"UNION POUR LA DEFENSE DES INTERETS DE LINAC","bord":"Divers","score":100.0,"color":"var(--div)"}]},{"code":"46175","nom":"Lissac-et-Mouret","inscrits":827,"votants":597,"participation":72.19,"status":"elu","bord":"indecis","candidats":[{"nom":"AGIR POUR LISSAC ET MOURET","parti":"AGIR POUR LISSAC ET MOURET","bord":"Divers","score":69.59,"color":"var(--div)"},{"nom":"NOUVEL ELAN POUR LISSAC-ET-MOURET","parti":"NOUVEL ELAN POUR LISSAC-ET-MOURET","bord":"Divers","score":30.41,"color":"var(--div)"}]},{"code":"46176","nom":"Livernon","inscrits":570,"votants":335,"participation":58.77,"status":"elu","bord":"indecis","candidats":[{"nom":"LIVERNON ENSEMBLE","parti":"LIVERNON ENSEMBLE","bord":"Divers","score":100.0,"color":"var(--div)"}]},{"code":"46177","nom":"Loubressac","inscrits":444,"votants":317,"participation":71.4,"status":"elu","bord":"indecis","candidats":[{"nom":"LOUBRESSAC ENSEMBLE","parti":"LOUBRESSAC ENSEMBLE","bord":"Divers","score":100.0,"color":"var(--div)"}]},{"code":"46178","nom":"Loupiac","inscrits":251,"votants":175,"participation":69.72,"status":"elu","bord":"indecis","candidats":[{"nom":"LOUPIAC, AUJOURD'HUI ET DEMAIN","parti":"LOUPIAC, AUJOURD'HUI ET DEMAIN","bord":"Divers","score":100.0,"color":"var(--div)"}]},{"code":"46179","nom":"Lugagnac","inscrits":149,"votants":113,"participation":75.84,"status":"elu","bord":"indecis","candidats":[{"nom":"Ensemble pour Lugagnac","parti":"Ensemble pour Lugagnac","bord":"Divers","score":100.0,"color":"var(--div)"}]},{"code":"46180","nom":"Lunan","inscrits":476,"votants":306,"participation":64.29,"status":"elu","bord":"indecis","candidats":[{"nom":"OBJECTIF LUNAN","parti":"OBJECTIF LUNAN","bord":"Divers","score":100.0,"color":"var(--div)"}]},{"code":"46181","nom":"Lunegarde","inscrits":88,"votants":51,"participation":57.95,"status":"elu","bord":"indecis","candidats":[{"nom":"ENSEMBLE POUR LUNEGARDE","parti":"ENSEMBLE POUR LUNEGARDE","bord":"Divers","score":100.0,"color":"var(--div)"}]},{"code":"46182","nom":"Luzech","inscrits":1321,"votants":966,"participation":73.13,"status":"elu","bord":"indecis","candidats":[{"nom":"Luzech Au Coeur","parti":"Luzech Au Coeur","bord":"Divers","score":56.21,"color":"var(--div)"},{"nom":"Agir pour Luzech","parti":"Agir pour Luzech","bord":"Divers","score":43.79,"color":"var(--div)"}]},{"code":"46183","nom":"Marcilhac-sur-Célé","inscrits":203,"votants":130,"participation":64.04,"status":"elu","bord":"indecis","candidats":[{"nom":"MARCILHAC VIVANT","parti":"MARCILHAC VIVANT","bord":"Divers","score":100.0,"color":"var(--div)"}]},{"code":"46184","nom":"Marminiac","inscrits":264,"votants":185,"participation":70.08,"status":"elu","bord":"indecis","candidats":[{"nom":"UNIS POUR MARMINIAC","parti":"UNIS POUR MARMINIAC","bord":"Divers","score":100.0,"color":"var(--div)"}]},{"code":"46185","nom":"Martel","inscrits":1398,"votants":883,"participation":63.16,"status":"elu","bord":"indecis","candidats":[{"nom":"POUR MARTEL","parti":"POUR MARTEL","bord":"Divers","score":100.0,"color":"var(--div)"}]},{"code":"46186","nom":"Masclat","inscrits":261,"votants":188,"participation":72.03,"status":"elu","bord":"indecis","candidats":[{"nom":"ENSEMBLE POUR MASCLAT","parti":"ENSEMBLE POUR MASCLAT","bord":"Divers","score":100.0,"color":"var(--div)"}]},{"code":"46187","nom":"Mauroux","inscrits":456,"votants":357,"participation":78.29,"status":"elu","bord":"indecis","candidats":[{"nom":"Mauroux l'avenir en commun","parti":"Mauroux l'avenir en commun","bord":"Divers","score":56.65,"color":"var(--div)"},{"nom":"Bien vivre à Mauroux","parti":"Bien vivre à Mauroux","bord":"Divers","score":43.35,"color":"var(--div)"}]},{"code":"46188","nom":"Maxou","inscrits":275,"votants":173,"participation":62.91,"status":"elu","bord":"indecis","candidats":[{"nom":"Agir et vivre ensemble pour notre commune","parti":"Agir et vivre ensemble pour notre commune","bord":"Divers","score":100.0,"color":"var(--div)"}]},{"code":"46189","nom":"Mayrinhac-Lentour","inscrits":437,"votants":376,"participation":86.04,"status":"elu","bord":"indecis","candidats":[{"nom":"NOTRE VILLAGE NOTRE AVENIR","parti":"NOTRE VILLAGE NOTRE AVENIR","bord":"Divers","score":59.4,"color":"var(--div)"},{"nom":"ENSEMBLE POUR MAYRINHAC","parti":"ENSEMBLE POUR MAYRINHAC","bord":"Divers","score":40.6,"color":"var(--div)"}]},{"code":"46190","nom":"Mechmont","inscrits":119,"votants":87,"participation":73.11,"status":"elu","bord":"indecis","candidats":[{"nom":"Bien Vivre à Mechmont","parti":"Bien Vivre à Mechmont","bord":"Divers","score":100.0,"color":"var(--div)"}]},{"code":"46191","nom":"Mercuès","inscrits":753,"votants":434,"participation":57.64,"status":"elu","bord":"indecis","candidats":[{"nom":"MERCUES AVENIR","parti":"MERCUES AVENIR","bord":"Divers","score":100.0,"color":"var(--div)"}]},{"code":"46192","nom":"Meyronne","inscrits":247,"votants":180,"participation":72.87,"status":"elu","bord":"indecis","candidats":[{"nom":"BIEN VIVRE À MEYRONNE","parti":"BIEN VIVRE À MEYRONNE","bord":"Divers","score":100.0,"color":"var(--div)"}]},{"code":"46193","nom":"Miers","inscrits":365,"votants":279,"participation":76.44,"status":"elu","bord":"indecis","candidats":[{"nom":"BIEN VIVRE À MIERS !","parti":"BIEN VIVRE À MIERS !","bord":"Divers","score":100.0,"color":"var(--div)"}]},{"code":"46194","nom":"Milhac","inscrits":197,"votants":130,"participation":65.99,"status":"elu","bord":"indecis","candidats":[{"nom":"UNIS POUR MILHAC","parti":"UNIS POUR MILHAC","bord":"Divers","score":100.0,"color":"var(--div)"}]},{"code":"46195","nom":"Molières","inscrits":288,"votants":220,"participation":76.39,"status":"elu","bord":"indecis","candidats":[{"nom":"ENSEMBLE POUR MOLIERES","parti":"ENSEMBLE POUR MOLIERES","bord":"Divers","score":100.0,"color":"var(--div)"}]},{"code":"46196","nom":"Montamel","inscrits":97,"votants":73,"participation":75.26,"status":"elu","bord":"indecis","candidats":[{"nom":"MONTAMEL À VENIR","parti":"MONTAMEL À VENIR","bord":"Divers","score":100.0,"color":"var(--div)"}]},{"code":"46197","nom":"Le Montat","inscrits":919,"votants":517,"participation":56.26,"status":"elu","bord":"indecis","candidats":[{"nom":"Bien vivre au Montat","parti":"Bien vivre au Montat","bord":"Divers","score":100.0,"color":"var(--div)"}]},{"code":"46198","nom":"Montbrun","inscrits":101,"votants":76,"participation":75.25,"status":"elu","bord":"indecis","candidats":[{"nom":"MONTBRUN L'AVENIR EN COMMUN","parti":"MONTBRUN L'AVENIR EN COMMUN","bord":"Divers","score":100.0,"color":"var(--div)"}]},{"code":"46199","nom":"Montcabrier","inscrits":279,"votants":208,"participation":74.55,"status":"elu","bord":"indecis","candidats":[{"nom":"Montcabrier pour tous","parti":"Montcabrier pour tous","bord":"Divers","score":100.0,"color":"var(--div)"}]},{"code":"46200","nom":"Montcléra","inscrits":243,"votants":213,"participation":87.65,"status":"elu","bord":"indecis","candidats":[{"nom":"ENSEMBLE A MONTCLERA","parti":"ENSEMBLE A MONTCLERA","bord":"Divers","score":50.48,"color":"var(--div)"},{"nom":"VIVRE ENSEMBLE","parti":"VIVRE ENSEMBLE","bord":"Divers","score":49.52,"color":"var(--div)"}]},{"code":"46201","nom":"Montcuq-en-Quercy-Blanc","inscrits":1428,"votants":1069,"participation":74.86,"status":"elu","bord":"indecis","candidats":[{"nom":"Continuité et développement","parti":"Continuité et développement","bord":"Divers","score":56.39,"color":"var(--div)"},{"nom":"Montcuq-en-Quercy-Blanc demain","parti":"Montcuq-en-Quercy-Blanc demain","bord":"Divers","score":43.61,"color":"var(--div)"}]},{"code":"46202","nom":"Montdoumerc","inscrits":428,"votants":354,"participation":82.71,"status":"elu","bord":"indecis","candidats":[{"nom":"Engagés pour un avenir dynamique et solidaire","parti":"Engagés pour un avenir dynamique et solidaire","bord":"Divers","score":85.39,"color":"var(--div)"},{"nom":"Ensemble, agissons pour Montdoumerc","parti":"Ensemble, agissons pour Montdoumerc","bord":"Divers","score":14.61,"color":"var(--div)"}]},{"code":"46203","nom":"Montet-et-Bouxal","inscrits":183,"votants":131,"participation":71.58,"status":"elu","bord":"indecis","candidats":[{"nom":"ENSEMBLE POUR MONTET ET BOUXAL","parti":"ENSEMBLE POUR MONTET ET BOUXAL","bord":"Divers","score":100.0,"color":"var(--div)"}]},{"code":"46204","nom":"Montfaucon","inscrits":329,"votants":217,"participation":65.96,"status":"elu","bord":"indecis","candidats":[{"nom":"MONTFAUCON, ENSEMBLE, CONTINUONS !","parti":"MONTFAUCON, ENSEMBLE, CONTINUONS !","bord":"Divers","score":100.0,"color":"var(--div)"}]},{"code":"46205","nom":"Montgesty","inscrits":283,"votants":185,"participation":65.37,"status":"elu","bord":"indecis","candidats":[{"nom":"Bien vivre ensemble à Montgesty","parti":"Bien vivre ensemble à Montgesty","bord":"Divers","score":100.0,"color":"var(--div)"}]},{"code":"46206","nom":"Montlauzun","inscrits":91,"votants":75,"participation":82.42,"status":"elu","bord":"indecis","candidats":[{"nom":"Bien vivre","parti":"Bien vivre","bord":"Divers","score":100.0,"color":"var(--div)"}]},{"code":"46207","nom":"Montredon","inscrits":195,"votants":144,"participation":73.85,"status":"elu","bord":"indecis","candidats":[{"nom":"Ensemble pour Montredon","parti":"Ensemble pour Montredon","bord":"Divers","score":100.0,"color":"var(--div)"}]},{"code":"46208","nom":"Montvalent","inscrits":282,"votants":192,"participation":68.09,"status":"elu","bord":"indecis","candidats":[{"nom":"MONTVALENT, EN AVANT !","parti":"MONTVALENT, EN AVANT !","bord":"Divers","score":100.0,"color":"var(--div)"}]},{"code":"46209","nom":"Nadaillac-de-Rouge","inscrits":166,"votants":126,"participation":75.9,"status":"elu","bord":"indecis","candidats":[{"nom":"BIEN VIVRE A NADAILLAC-DE-ROUGE UNE NOUVELLE ÉQUIPE S'ENGAGE !","parti":"BIEN VIVRE A NADAILLAC-DE-ROUGE UNE NOUVELLE ÉQUIPE S'ENGAGE !","bord":"Divers","score":100.0,"color":"var(--div)"}]},{"code":"46210","nom":"Nadillac","inscrits":63,"votants":46,"participation":73.02,"status":"elu","bord":"indecis","candidats":[{"nom":"ENSEMBLE","parti":"ENSEMBLE","bord":"Divers","score":100.0,"color":"var(--div)"}]},{"code":"46211","nom":"Nuzéjouls","inscrits":291,"votants":218,"participation":74.91,"status":"elu","bord":"indecis","candidats":[{"nom":"ENSEMBLE BATISSONS DEMAIN","parti":"ENSEMBLE BATISSONS DEMAIN","bord":"Divers","score":100.0,"color":"var(--div)"}]},{"code":"46212","nom":"Orniac","inscrits":76,"votants":50,"participation":65.79,"status":"elu","bord":"indecis","candidats":[{"nom":"LISTE ORNIAC","parti":"LISTE ORNIAC","bord":"Divers","score":100.0,"color":"var(--div)"}]},{"code":"46213","nom":"Padirac","inscrits":153,"votants":114,"participation":74.51,"status":"elu","bord":"indecis","candidats":[{"nom":"UN NOUVEL ÉLAN POUR PADIRAC","parti":"UN NOUVEL ÉLAN POUR PADIRAC","bord":"Divers","score":100.0,"color":"var(--div)"}]},{"code":"46214","nom":"Parnac","inscrits":328,"votants":229,"participation":69.82,"status":"elu","bord":"indecis","candidats":[{"nom":"Ensemble pour l'avenir de Parnac","parti":"Ensemble pour l'avenir de Parnac","bord":"Divers","score":100.0,"color":"var(--div)"}]},{"code":"46215","nom":"Payrac","inscrits":593,"votants":361,"participation":60.88,"status":"elu","bord":"indecis","candidats":[{"nom":"PAYRAC 2026","parti":"PAYRAC 2026","bord":"Divers","score":100.0,"color":"var(--div)"}]},{"code":"46216","nom":"Payrignac","inscrits":642,"votants":472,"participation":73.52,"status":"elu","bord":"indecis","candidats":[{"nom":"PAYRIGNAC DEMAIN","parti":"PAYRIGNAC DEMAIN","bord":"Divers","score":61.67,"color":"var(--div)"},{"nom":"CHOISIR ENSEMBLE PAYRIGNAC","parti":"CHOISIR ENSEMBLE PAYRIGNAC","bord":"Divers","score":38.33,"color":"var(--div)"}]},{"code":"46218","nom":"Pescadoires","inscrits":120,"votants":78,"participation":65.0,"status":"elu","bord":"indecis","candidats":[{"nom":"Unis pour Pescadoires","parti":"Unis pour Pescadoires","bord":"Divers","score":100.0,"color":"var(--div)"}]},{"code":"46219","nom":"Peyrilles","inscrits":354,"votants":241,"participation":68.08,"status":"elu","bord":"indecis","candidats":[{"nom":"PEYRILLES - UNIS POUR DEMAIN","parti":"PEYRILLES - UNIS POUR DEMAIN","bord":"Divers","score":100.0,"color":"var(--div)"}]},{"code":"46220","nom":"Pinsac","inscrits":675,"votants":531,"participation":78.67,"status":"elu","bord":"indecis","candidats":[{"nom":"AGIR POUR PINSAC","parti":"AGIR POUR PINSAC","bord":"Divers","score":51.65,"color":"var(--div)"},{"nom":"ENSEMBLE POUR L'AVENIR DE PINSAC","parti":"ENSEMBLE POUR L'AVENIR DE PINSAC","bord":"Divers","score":48.35,"color":"var(--div)"}]},{"code":"46221","nom":"Planioles","inscrits":431,"votants":315,"participation":73.09,"status":"elu","bord":"indecis","candidats":[{"nom":"BIEN VIVRE A PLANIOLES","parti":"BIEN VIVRE A PLANIOLES","bord":"Divers","score":60.13,"color":"var(--div)"},{"nom":"PLANIOLES DECOLLE","parti":"PLANIOLES DECOLLE","bord":"Divers","score":39.87,"color":"var(--div)"}]},{"code":"46222","nom":"Pomarède","inscrits":140,"votants":102,"participation":72.86,"status":"elu","bord":"indecis","candidats":[{"nom":"ENSEMBLE POUR POMARÈDE","parti":"ENSEMBLE POUR POMARÈDE","bord":"Divers","score":100.0,"color":"var(--div)"}]},{"code":"46223","nom":"Pontcirq","inscrits":157,"votants":119,"participation":75.8,"status":"elu","bord":"indecis","candidats":[{"nom":"PONTCIRQ ENSEMBLE","parti":"PONTCIRQ ENSEMBLE","bord":"Divers","score":100.0,"color":"var(--div)"}]},{"code":"46224","nom":"Pradines","inscrits":2780,"votants":1728,"participation":62.16,"status":"elu","bord":"indecis","candidats":[{"nom":"Vivons Pradines ensemble","parti":"Vivons Pradines ensemble","bord":"Divers","score":53.71,"color":"var(--div)"},{"nom":"Demain Pradines","parti":"Demain Pradines","bord":"Gauche","score":46.29,"color":"var(--ps)"}]},{"code":"46225","nom":"Prayssac","inscrits":2054,"votants":1134,"participation":55.21,"status":"elu","bord":"indecis","candidats":[{"nom":"Vivons Prayssac","parti":"Vivons Prayssac","bord":"Divers","score":100.0,"color":"var(--div)"}]},{"code":"46226","nom":"Prendeignes","inscrits":173,"votants":121,"participation":69.94,"status":"elu","bord":"indecis","candidats":[{"nom":"PRENDEIGNES : VIVRE ET AGIR ENSEMBLE","parti":"PRENDEIGNES : VIVRE ET AGIR ENSEMBLE","bord":"Divers","score":100.0,"color":"var(--div)"}]},{"code":"46227","nom":"Promilhanes","inscrits":193,"votants":141,"participation":73.06,"status":"elu","bord":"indecis","candidats":[{"nom":"Ensemble pour Promilhanes","parti":"Ensemble pour Promilhanes","bord":"Divers","score":100.0,"color":"var(--div)"}]},{"code":"46228","nom":"Prudhomat","inscrits":633,"votants":428,"participation":67.61,"status":"elu","bord":"indecis","candidats":[{"nom":"PRUDHOMAT ENSEMBLE","parti":"PRUDHOMAT ENSEMBLE","bord":"Divers","score":100.0,"color":"var(--div)"}]},{"code":"46229","nom":"Puybrun","inscrits":770,"votants":457,"participation":59.35,"status":"elu","bord":"indecis","candidats":[{"nom":"VIVRE ET AGIR ENSEMBLE A PUYBRUN","parti":"VIVRE ET AGIR ENSEMBLE A PUYBRUN","bord":"Divers","score":100.0,"color":"var(--div)"}]},{"code":"46230","nom":"Puyjourdes","inscrits":87,"votants":74,"participation":85.06,"status":"elu","bord":"indecis","candidats":[{"nom":"PUYJOURDES EN COMMUN","parti":"PUYJOURDES EN COMMUN","bord":"Divers","score":100.0,"color":"var(--div)"}]},{"code":"46231","nom":"Puy-l'Evêque","inscrits":1480,"votants":807,"participation":54.53,"status":"elu","bord":"indecis","candidats":[{"nom":"Ensemble pour Puy-L'Evêque","parti":"Ensemble pour Puy-L'Evêque","bord":"Divers","score":100.0,"color":"var(--div)"}]},{"code":"46232","nom":"Le Vignon-en-Quercy","inscrits":742,"votants":414,"participation":55.8,"status":"elu","bord":"indecis","candidats":[{"nom":"POURSUIVONS ENSEMBLE","parti":"POURSUIVONS ENSEMBLE","bord":"Divers","score":100.0,"color":"var(--div)"}]},{"code":"46233","nom":"Quissac-en-Quercy","inscrits":100,"votants":66,"participation":66.0,"status":"elu","bord":"indecis","candidats":[{"nom":"ENSEMBLE POUR QUISSAC","parti":"ENSEMBLE POUR QUISSAC","bord":"Divers","score":100.0,"color":"var(--div)"}]},{"code":"46234","nom":"Rampoux","inscrits":95,"votants":70,"participation":73.68,"status":"elu","bord":"indecis","candidats":[{"nom":"ENSEMBLE POUR RAMPOUX","parti":"ENSEMBLE POUR RAMPOUX","bord":"Divers","score":100.0,"color":"var(--div)"}]},{"code":"46235","nom":"Reilhac","inscrits":136,"votants":105,"participation":77.21,"status":"elu","bord":"indecis","candidats":[{"nom":"Reilhac, un village que nous faisons vivre ensemble","parti":"Reilhac, un village que nous faisons vivre ensemble","bord":"Divers","score":100.0,"color":"var(--div)"}]},{"code":"46236","nom":"Reilhaguet","inscrits":166,"votants":121,"participation":72.89,"status":"elu","bord":"indecis","candidats":[{"nom":"UNIS POUR REILHAGUET, LAVAL ET SES HAMEAUX","parti":"UNIS POUR REILHAGUET, LAVAL ET SES HAMEAUX","bord":"Divers","score":100.0,"color":"var(--div)"}]},{"code":"46237","nom":"Reyrevignes","inscrits":323,"votants":226,"participation":69.97,"status":"elu","bord":"indecis","candidats":[{"nom":"REYREVIGNES 2026","parti":"REYREVIGNES 2026","bord":"Divers","score":100.0,"color":"var(--div)"}]},{"code":"46238","nom":"Rignac","inscrits":268,"votants":229,"participation":85.45,"status":"elu","bord":"indecis","candidats":[{"nom":"PRÉSERVER NOTRE VILLAGE, BÂTIR VOTRE DEMAIN","parti":"PRÉSERVER NOTRE VILLAGE, BÂTIR VOTRE DEMAIN","bord":"Divers","score":57.59,"color":"var(--div)"},{"nom":"RIGNAC, NOTRE VILLAGE, NOTRE AVENIR","parti":"RIGNAC, NOTRE VILLAGE, NOTRE AVENIR","bord":"Divers","score":42.41,"color":"var(--div)"}]},{"code":"46239","nom":"Le Roc","inscrits":205,"votants":189,"participation":92.2,"status":"elu","bord":"indecis","candidats":[{"nom":"LE ROC ENSEMBLE","parti":"LE ROC ENSEMBLE","bord":"Divers","score":54.3,"color":"var(--div)"},{"nom":"UNIS POUR LE ROC","parti":"UNIS POUR LE ROC","bord":"Divers","score":45.7,"color":"var(--div)"}]},{"code":"46240","nom":"Rocamadour","inscrits":534,"votants":409,"participation":76.59,"status":"elu","bord":"indecis","candidats":[{"nom":"ROCAMADOUR, ENSEMBLE POUR L'AVENIR","parti":"ROCAMADOUR, ENSEMBLE POUR L'AVENIR","bord":"Divers","score":69.87,"color":"var(--div)"},{"nom":"ROCAVENIR","parti":"ROCAVENIR","bord":"Divers","score":30.13,"color":"var(--div)"}]},{"code":"46241","nom":"Rouffilhac","inscrits":181,"votants":138,"participation":76.24,"status":"elu","bord":"indecis","candidats":[{"nom":"ROUFFILHAC NOTRE VILLAGE OU IL FAIT BON VIVRE","parti":"ROUFFILHAC NOTRE VILLAGE OU IL FAIT BON VIVRE","bord":"Divers","score":100.0,"color":"var(--div)"}]},{"code":"46242","nom":"Rudelle","inscrits":166,"votants":123,"participation":74.1,"status":"elu","bord":"indecis","candidats":[{"nom":"RUDELLE ENSEMBLE","parti":"RUDELLE ENSEMBLE","bord":"Divers","score":100.0,"color":"var(--div)"}]},{"code":"46243","nom":"Rueyres","inscrits":163,"votants":93,"participation":57.06,"status":"elu","bord":"indecis","candidats":[{"nom":"LISTE POUR LA DEFENSE DES INTERETS COMMUNAUX","parti":"LISTE POUR LA DEFENSE DES INTERETS COMMUNAUX","bord":"Divers","score":100.0,"color":"var(--div)"}]},{"code":"46244","nom":"Sabadel-Latronquière","inscrits":80,"votants":63,"participation":78.75,"status":"elu","bord":"indecis","candidats":[{"nom":"SABADEL-LAT DEMAIN","parti":"SABADEL-LAT DEMAIN","bord":"Divers","score":100.0,"color":"var(--div)"}]},{"code":"46245","nom":"Sabadel-Lauzès","inscrits":90,"votants":85,"participation":94.44,"status":"elu","bord":"indecis","candidats":[{"nom":"SABADEL POUR TOUS","parti":"SABADEL POUR TOUS","bord":"Divers","score":65.06,"color":"var(--div)"},{"nom":"VIVRE ENSEMBLE SABADEL","parti":"VIVRE ENSEMBLE SABADEL","bord":"Divers","score":34.94,"color":"var(--div)"}]},{"code":"46246","nom":"Saignes","inscrits":63,"votants":45,"participation":71.43,"status":"elu","bord":"indecis","candidats":[{"nom":"LISTE D'UNION POUR SAIGNES","parti":"LISTE D'UNION POUR SAIGNES","bord":"Divers","score":100.0,"color":"var(--div)"}]},{"code":"46247","nom":"Saillac","inscrits":148,"votants":125,"participation":84.46,"status":"elu","bord":"indecis","candidats":[{"nom":"Saillac-Jamblusse, avec tous, pour tous","parti":"Saillac-Jamblusse, avec tous, pour tous","bord":"Divers","score":59.68,"color":"var(--div)"},{"nom":"Agissons ensemble pour notre territoire","parti":"Agissons ensemble pour notre territoire","bord":"Divers","score":40.32,"color":"var(--div)"}]},{"code":"46249","nom":"Saint-Bressou","inscrits":125,"votants":89,"participation":71.2,"status":"elu","bord":"indecis","candidats":[{"nom":"SAINT-BRESSOU C'EST VOUS ET NOUS","parti":"SAINT-BRESSOU C'EST VOUS ET NOUS","bord":"Divers","score":100.0,"color":"var(--div)"}]},{"code":"46250","nom":"Saint-Caprais","inscrits":80,"votants":57,"participation":71.25,"status":"elu","bord":"indecis","candidats":[{"nom":"AVENIR SAINT-CAPRAIS","parti":"AVENIR SAINT-CAPRAIS","bord":"Divers","score":100.0,"color":"var(--div)"}]},{"code":"46251","nom":"Saint-Céré","inscrits":2492,"votants":1735,"participation":69.62,"status":"elu","bord":"indecis","candidats":[{"nom":"Ensemble, relançons Saint-Céré","parti":"Ensemble, relançons Saint-Céré","bord":"Divers","score":65.8,"color":"var(--div)"},{"nom":"SAINT-CERE EN HARMONIE 2026","parti":"SAINT-CERE EN HARMONIE 2026","bord":"Divers","score":34.2,"color":"var(--div)"}]},{"code":"46252","nom":"Les Pechs du Vers","inscrits":303,"votants":196,"participation":64.69,"status":"elu","bord":"indecis","candidats":[{"nom":"LES PECHS DU VERS, VILLAGES D'AVENIR","parti":"LES PECHS DU VERS, VILLAGES D'AVENIR","bord":"Divers","score":100.0,"color":"var(--div)"}]},{"code":"46253","nom":"Saint-Chamarand","inscrits":184,"votants":125,"participation":67.93,"status":"elu","bord":"indecis","candidats":[{"nom":"ENSEMBLE POUR SAINT-CHAMARAND","parti":"ENSEMBLE POUR SAINT-CHAMARAND","bord":"Divers","score":100.0,"color":"var(--div)"}]},{"code":"46254","nom":"Saint-Chels","inscrits":144,"votants":111,"participation":77.08,"status":"elu","bord":"indecis","candidats":[{"nom":"ENSEMBLE POUR SAINT CHELS","parti":"ENSEMBLE POUR SAINT CHELS","bord":"Divers","score":100.0,"color":"var(--div)"}]},{"code":"46255","nom":"Saint-Cirgues","inscrits":324,"votants":279,"participation":86.11,"status":"elu","bord":"indecis","candidats":[{"nom":"ENSEMBLE CONSTRUISONS L'AVENIR","parti":"ENSEMBLE CONSTRUISONS L'AVENIR","bord":"Divers","score":50.18,"color":"var(--div)"},{"nom":"SAINT CIRGUES POUR TOUS","parti":"SAINT CIRGUES POUR TOUS","bord":"Divers","score":49.82,"color":"var(--div)"}]},{"code":"46256","nom":"Saint-Cirq-Lapopie","inscrits":234,"votants":174,"participation":74.36,"status":"elu","bord":"indecis","candidats":[{"nom":"Saint-Cirq-Lapopie avec passion","parti":"Saint-Cirq-Lapopie avec passion","bord":"Divers","score":100.0,"color":"var(--div)"}]},{"code":"46257","nom":"Saint-Cirq-Madelon","inscrits":121,"votants":81,"participation":66.94,"status":"elu","bord":"indecis","candidats":[{"nom":"AGIR POUR SAINT-CIRQ-MADELON","parti":"AGIR POUR SAINT-CIRQ-MADELON","bord":"Divers","score":100.0,"color":"var(--div)"}]},{"code":"46258","nom":"Saint-Cirq-Souillaguet","inscrits":153,"votants":114,"participation":74.51,"status":"elu","bord":"indecis","candidats":[{"nom":"UNIS DANS UN MÊME ELAN","parti":"UNIS DANS UN MÊME ELAN","bord":"Divers","score":100.0,"color":"var(--div)"}]},{"code":"46259","nom":"Saint-Clair","inscrits":145,"votants":140,"participation":96.55,"status":"elu","bord":"indecis","candidats":[{"nom":"UN NOUVEL ELAN","parti":"UN NOUVEL ELAN","bord":"Divers","score":52.21,"color":"var(--div)"},{"nom":"CONTINUONS ENSEMBLE","parti":"CONTINUONS ENSEMBLE","bord":"Divers","score":47.79,"color":"var(--div)"}]},{"code":"46260","nom":"Sainte-Colombe","inscrits":196,"votants":138,"participation":70.41,"status":"elu","bord":"indecis","candidats":[{"nom":"ENSEMBLE POUR SAINTE-COLOMBE","parti":"ENSEMBLE POUR SAINTE-COLOMBE","bord":"Divers","score":100.0,"color":"var(--div)"}]},{"code":"46262","nom":"Lendou-en-Quercy","inscrits":532,"votants":332,"participation":62.41,"status":"elu","bord":"indecis","candidats":[{"nom":"Lendou en Quercy pour tous","parti":"Lendou en Quercy pour tous","bord":"Divers","score":100.0,"color":"var(--div)"}]},{"code":"46263","nom":"Barguelonne-en-Quercy","inscrits":611,"votants":463,"participation":75.78,"status":"elu","bord":"indecis","candidats":[{"nom":"Avancer ensemble","parti":"Avancer ensemble","bord":"Divers","score":53.44,"color":"var(--div)"},{"nom":"Demain avec vous","parti":"Demain avec vous","bord":"Divers","score":46.56,"color":"var(--div)"}]},{"code":"46264","nom":"Saint-Denis-Catus","inscrits":178,"votants":146,"participation":82.02,"status":"elu","bord":"indecis","candidats":[{"nom":"Saint-Denis-Catus 2026","parti":"Saint-Denis-Catus 2026","bord":"Divers","score":52.08,"color":"var(--div)"},{"nom":"Ensemble pour l'Avenir de Saint-Denis-Catus","parti":"Ensemble pour l'Avenir de Saint-Denis-Catus","bord":"Divers","score":47.92,"color":"var(--div)"}]},{"code":"46265","nom":"Saint-Denis-lès-Martel","inscrits":278,"votants":177,"participation":63.67,"status":"elu","bord":"indecis","candidats":[{"nom":"LES DIONYSIENS AU QUOTIDIEN","parti":"LES DIONYSIENS AU QUOTIDIEN","bord":"Divers","score":100.0,"color":"var(--div)"}]},{"code":"46266","nom":"Saint-Félix","inscrits":397,"votants":292,"participation":73.55,"status":"elu","bord":"indecis","candidats":[{"nom":"SAINT-FELIX EN COMMUN","parti":"SAINT-FELIX EN COMMUN","bord":"Divers","score":100.0,"color":"var(--div)"}]},{"code":"46267","nom":"Saint-Germain-du-Bel-Air","inscrits":482,"votants":316,"participation":65.56,"status":"elu","bord":"indecis","candidats":[{"nom":"VIVRE SAINT-GERMAIN, AGIR POUR DEMAIN","parti":"VIVRE SAINT-GERMAIN, AGIR POUR DEMAIN","bord":"Divers","score":100.0,"color":"var(--div)"}]},{"code":"46268","nom":"Saint Géry-Vers","inscrits":772,"votants":432,"participation":55.96,"status":"elu","bord":"indecis","candidats":[{"nom":"Continuons ensemble pour notre commune","parti":"Continuons ensemble pour notre commune","bord":"Divers","score":100.0,"color":"var(--div)"}]},{"code":"46269","nom":"Saint-Hilaire","inscrits":71,"votants":46,"participation":64.79,"status":"elu","bord":"indecis","candidats":[{"nom":"CONSTRUIRE ENSEMBLE L'AVENIR DE SAINT-HILAIRE","parti":"CONSTRUIRE ENSEMBLE L'AVENIR DE SAINT-HILAIRE","bord":"Divers","score":100.0,"color":"var(--div)"}]},{"code":"46270","nom":"Saint-Jean-de-Laur","inscrits":238,"votants":182,"participation":76.47,"status":"elu","bord":"indecis","candidats":[{"nom":"NOTRE VILLAGE, NOTRE AVENIR","parti":"NOTRE VILLAGE, NOTRE AVENIR","bord":"Divers","score":100.0,"color":"var(--div)"}]},{"code":"46271","nom":"Saint-Jean-Lespinasse","inscrits":342,"votants":214,"participation":62.57,"status":"elu","bord":"indecis","candidats":[{"nom":"ENSEMBLE POUR SAINT JEAN","parti":"ENSEMBLE POUR SAINT JEAN","bord":"Divers","score":100.0,"color":"var(--div)"}]},{"code":"46272","nom":"Saint-Jean-Mirabel","inscrits":184,"votants":146,"participation":79.35,"status":"elu","bord":"indecis","candidats":[{"nom":"UNIS POUR UN PROJET D'AVENIR","parti":"UNIS POUR UN PROJET D'AVENIR","bord":"Divers","score":100.0,"color":"var(--div)"}]},{"code":"46273","nom":"Saint-Laurent-les-Tours","inscrits":770,"votants":533,"participation":69.22,"status":"elu","bord":"indecis","candidats":[{"nom":"ENSEMBLE CONTINUONS","parti":"ENSEMBLE CONTINUONS","bord":"Divers","score":100.0,"color":"var(--div)"}]},{"code":"46276","nom":"Saint-Martin-Labouval","inscrits":157,"votants":122,"participation":77.71,"status":"elu","bord":"indecis","candidats":[{"nom":"Saint-Martin-Labouval, un avenir partagé","parti":"Saint-Martin-Labouval, un avenir partagé","bord":"Divers","score":100.0,"color":"var(--div)"}]},{"code":"46277","nom":"Saint-Martin-le-Redon","inscrits":189,"votants":121,"participation":64.02,"status":"elu","bord":"indecis","candidats":[{"nom":"Ensemble, continuons d'agir pour Saint-Martin-le-Redon","parti":"Ensemble, continuons d'agir pour Saint-Martin-le-Redon","bord":"Divers","score":100.0,"color":"var(--div)"}]},{"code":"46279","nom":"Saint-Maurice-en-Quercy","inscrits":165,"votants":126,"participation":76.36,"status":"elu","bord":"indecis","candidats":[{"nom":"Liste d'union pour l'Avenir de Saint-Maurice","parti":"Liste d'union pour l'Avenir de Saint-Maurice","bord":"Divers","score":100.0,"color":"var(--div)"}]},{"code":"46280","nom":"Saint-Médard","inscrits":169,"votants":111,"participation":65.68,"status":"elu","bord":"indecis","candidats":[{"nom":"Avec vous pour Saint-Médard","parti":"Avec vous pour Saint-Médard","bord":"Divers","score":100.0,"color":"var(--div)"}]},{"code":"46281","nom":"Saint-Médard-de-Presque","inscrits":186,"votants":169,"participation":90.86,"status":"elu","bord":"indecis","candidats":[{"nom":"AGISSONS ENSEMBLE POUR SAINT-MEDARD-DE-PRESQUE","parti":"AGISSONS ENSEMBLE POUR SAINT-MEDARD-DE-PRESQUE","bord":"Divers","score":51.5,"color":"var(--div)"},{"nom":"TOUTES ET TOUS POUR L'AVENIR DE SAINT MEDARD","parti":"TOUTES ET TOUS POUR L'AVENIR DE SAINT MEDARD","bord":"Divers","score":48.5,"color":"var(--div)"}]},{"code":"46282","nom":"Saint-Médard-Nicourby","inscrits":70,"votants":60,"participation":85.71,"status":"elu","bord":"indecis","candidats":[{"nom":"liste d'union républicaine de défense des intérêts communaux","parti":"liste d'union républicaine de défense des intérêts communaux","bord":"Divers","score":100.0,"color":"var(--div)"}]},{"code":"46283","nom":"Saint-Michel-de-Bannières","inscrits":286,"votants":200,"participation":69.93,"status":"elu","bord":"indecis","candidats":[{"nom":"AGIR ET VIVRE ENSEMBLE","parti":"AGIR ET VIVRE ENSEMBLE","bord":"Divers","score":100.0,"color":"var(--div)"}]},{"code":"46284","nom":"Saint-Michel-Loubéjou","inscrits":329,"votants":215,"participation":65.35,"status":"elu","bord":"indecis","candidats":[{"nom":"UN ENGAGEMENT POUR TOUS","parti":"UN ENGAGEMENT POUR TOUS","bord":"Divers","score":100.0,"color":"var(--div)"}]},{"code":"46286","nom":"Saint-Paul-de-Vern","inscrits":146,"votants":120,"participation":82.19,"status":"elu","bord":"indecis","candidats":[{"nom":"UN VILLAGE UNE EQUIPE DES PROJETS","parti":"UN VILLAGE UNE EQUIPE DES PROJETS","bord":"Divers","score":100.0,"color":"var(--div)"}]},{"code":"46288","nom":"Saint-Perdoux","inscrits":173,"votants":109,"participation":63.01,"status":"elu","bord":"indecis","candidats":[{"nom":"SAINT-PERDOUX, UN AVENIR EN COMMUN !","parti":"SAINT-PERDOUX, UN AVENIR EN COMMUN !","bord":"Divers","score":100.0,"color":"var(--div)"}]},{"code":"46289","nom":"Saint-Pierre-Toirac","inscrits":120,"votants":83,"participation":69.17,"status":"elu","bord":"indecis","candidats":[{"nom":"BRIX","parti":"BRIX","bord":"Divers","score":100.0,"color":"var(--div)"}]},{"code":"46290","nom":"Saint-Projet","inscrits":289,"votants":203,"participation":70.24,"status":"elu","bord":"indecis","candidats":[{"nom":"SAINT-PROJET, NOTRE VILLAGE, NOTRE AVENIR","parti":"SAINT-PROJET, NOTRE VILLAGE, NOTRE AVENIR","bord":"Divers","score":100.0,"color":"var(--div)"}]},{"code":"46292","nom":"Saint-Simon","inscrits":155,"votants":101,"participation":65.16,"status":"elu","bord":"indecis","candidats":[{"nom":"POUR SAINT-SIMON","parti":"POUR SAINT-SIMON","bord":"Divers","score":100.0,"color":"var(--div)"}]},{"code":"46293","nom":"Saint-Sozy","inscrits":432,"votants":266,"participation":61.57,"status":"elu","bord":"indecis","candidats":[{"nom":"RACINE ET AVENIR","parti":"RACINE ET AVENIR","bord":"Divers","score":100.0,"color":"var(--div)"}]},{"code":"46294","nom":"Saint-Sulpice","inscrits":137,"votants":83,"participation":60.58,"status":"elu","bord":"indecis","candidats":[{"nom":"POUR SAINT-SULPICE","parti":"POUR SAINT-SULPICE","bord":"Divers","score":100.0,"color":"var(--div)"}]},{"code":"46295","nom":"Saint-Vincent-du-Pendit","inscrits":173,"votants":127,"participation":73.41,"status":"elu","bord":"indecis","candidats":[{"nom":"VIVONS ENSEMBLE A SAINT VINCENT","parti":"VIVONS ENSEMBLE A SAINT VINCENT","bord":"Divers","score":100.0,"color":"var(--div)"}]},{"code":"46296","nom":"Saint-Vincent-Rive-d'Olt","inscrits":432,"votants":344,"participation":79.63,"status":"elu","bord":"indecis","candidats":[{"nom":"Ensemble pour demain","parti":"Ensemble pour demain","bord":"Divers","score":61.68,"color":"var(--div)"},{"nom":"Pour le bien et l'unité de Saint-Vincent","parti":"Pour le bien et l'unité de Saint-Vincent","bord":"Divers","score":38.32,"color":"var(--div)"}]},{"code":"46297","nom":"Salviac","inscrits":1068,"votants":697,"participation":65.26,"status":"elu","bord":"indecis","candidats":[{"nom":"DEMAIN SALVIAC","parti":"DEMAIN SALVIAC","bord":"Divers","score":100.0,"color":"var(--div)"}]},{"code":"46299","nom":"Sauliac-sur-Célé","inscrits":119,"votants":76,"participation":63.87,"status":"elu","bord":"indecis","candidats":[{"nom":"ENSEMBLE POUR SAULIAC","parti":"ENSEMBLE POUR SAULIAC","bord":"Divers","score":100.0,"color":"var(--div)"}]},{"code":"46301","nom":"Sauzet","inscrits":370,"votants":248,"participation":67.03,"status":"elu","bord":"indecis","candidats":[{"nom":"Bien vivre à Sauzet","parti":"Bien vivre à Sauzet","bord":"Divers","score":100.0,"color":"var(--div)"}]},{"code":"46302","nom":"Sénaillac-Latronquière","inscrits":125,"votants":86,"participation":68.8,"status":"elu","bord":"indecis","candidats":[{"nom":"Commune Sénaillac-Latronquière","parti":"Commune Sénaillac-Latronquière","bord":"Divers","score":100.0,"color":"var(--div)"}]},{"code":"46303","nom":"Sénaillac-Lauzès","inscrits":148,"votants":114,"participation":77.03,"status":"elu","bord":"indecis","candidats":[{"nom":"UNIS POUR L'AVENIR DE LA COMMUNE","parti":"UNIS POUR L'AVENIR DE LA COMMUNE","bord":"Divers","score":100.0,"color":"var(--div)"}]},{"code":"46304","nom":"Séniergues","inscrits":117,"votants":91,"participation":77.78,"status":"elu","bord":"indecis","candidats":[{"nom":"AGIR POUR SÉNIERGUES","parti":"AGIR POUR SÉNIERGUES","bord":"Divers","score":100.0,"color":"var(--div)"}]},{"code":"46305","nom":"Sérignac","inscrits":306,"votants":274,"participation":89.54,"status":"elu","bord":"indecis","candidats":[{"nom":"Un nouvel élan","parti":"Un nouvel élan","bord":"Divers","score":51.7,"color":"var(--div)"},{"nom":"PENSER GLOBAL, AGIR LOCAL ENSEMBLE","parti":"PENSER GLOBAL, AGIR LOCAL ENSEMBLE","bord":"Divers","score":48.3,"color":"var(--div)"}]},{"code":"46306","nom":"Sonac","inscrits":94,"votants":73,"participation":77.66,"status":"elu","bord":"indecis","candidats":[{"nom":"TOUS ENSEMBLE POUR SONAC","parti":"TOUS ENSEMBLE POUR SONAC","bord":"Divers","score":100.0,"color":"var(--div)"}]},{"code":"46307","nom":"Soturac","inscrits":504,"votants":293,"participation":58.13,"status":"elu","bord":"indecis","candidats":[{"nom":"Ensemble pour les intérêts communaux","parti":"Ensemble pour les intérêts communaux","bord":"Divers","score":100.0,"color":"var(--div)"}]},{"code":"46308","nom":"Soucirac","inscrits":113,"votants":98,"participation":86.73,"status":"elu","bord":"indecis","candidats":[{"nom":"AVEC SOUCIRAC","parti":"AVEC SOUCIRAC","bord":"Divers","score":51.55,"color":"var(--div)"},{"nom":"TOUS ENSEMBLE POUR SOUCIRAC","parti":"TOUS ENSEMBLE POUR SOUCIRAC","bord":"Divers","score":48.45,"color":"var(--div)"}]},{"code":"46309","nom":"Souillac","inscrits":2308,"votants":1498,"participation":64.9,"status":"2t","bord":"indecis","candidats":[{"nom":"SOUILLAC L'AMBITION DE VIVRE MIEUX","parti":"SOUILLAC L'AMBITION DE VIVRE MIEUX","bord":"Divers","score":44.78,"color":"var(--div)"},{"nom":"VIVONS SOUILLAC","parti":"VIVONS SOUILLAC","bord":"Divers","score":41.41,"color":"var(--div)"},{"nom":"VIVRE ENSEMBLE À SOUILLAC","parti":"VIVRE ENSEMBLE À SOUILLAC","bord":"Divers","score":13.8,"color":"var(--div)"}]},{"code":"46310","nom":"Soulomès","inscrits":120,"votants":94,"participation":78.33,"status":"elu","bord":"indecis","candidats":[{"nom":"BIEN VIVRE A SOULOMÈS","parti":"BIEN VIVRE A SOULOMÈS","bord":"Divers","score":100.0,"color":"var(--div)"}]},{"code":"46311","nom":"Sousceyrac-en-Quercy","inscrits":1134,"votants":774,"participation":68.25,"status":"elu","bord":"indecis","candidats":[{"nom":"VOS VOIX NOTRE FORCE","parti":"VOS VOIX NOTRE FORCE","bord":"Divers","score":100.0,"color":"var(--div)"}]},{"code":"46312","nom":"Strenquels","inscrits":224,"votants":157,"participation":70.09,"status":"elu","bord":"indecis","candidats":[{"nom":"ENSEMBLE POUR STRENQUELS","parti":"ENSEMBLE POUR STRENQUELS","bord":"Divers","score":100.0,"color":"var(--div)"}]},{"code":"46313","nom":"Tauriac","inscrits":347,"votants":233,"participation":67.15,"status":"elu","bord":"indecis","candidats":[{"nom":"agir ensemble pour tauriac","parti":"agir ensemble pour tauriac","bord":"Divers","score":100.0,"color":"var(--div)"}]},{"code":"46314","nom":"Terrou","inscrits":156,"votants":107,"participation":68.59,"status":"elu","bord":"indecis","candidats":[{"nom":"AGIR POUR TERROU","parti":"AGIR POUR TERROU","bord":"Divers","score":100.0,"color":"var(--div)"}]},{"code":"46315","nom":"Teyssieu","inscrits":158,"votants":115,"participation":72.78,"status":"elu","bord":"indecis","candidats":[{"nom":"VIVONS TEYSSIEU","parti":"VIVONS TEYSSIEU","bord":"Divers","score":100.0,"color":"var(--div)"}]},{"code":"46316","nom":"Thédirac","inscrits":249,"votants":149,"participation":59.84,"status":"elu","bord":"indecis","candidats":[{"nom":"ENSEMBLE POUR THÉDIRAC","parti":"ENSEMBLE POUR THÉDIRAC","bord":"Divers","score":100.0,"color":"var(--div)"}]},{"code":"46317","nom":"Thégra","inscrits":397,"votants":258,"participation":64.99,"status":"elu","bord":"indecis","candidats":[{"nom":"UN SOUFFLE NOUVEAU POUR THÉGRA","parti":"UN SOUFFLE NOUVEAU POUR THÉGRA","bord":"Divers","score":100.0,"color":"var(--div)"}]},{"code":"46318","nom":"Thémines","inscrits":227,"votants":149,"participation":65.64,"status":"elu","bord":"indecis","candidats":[{"nom":"BON SENS POUR THEMINES","parti":"BON SENS POUR THEMINES","bord":"Divers","score":100.0,"color":"var(--div)"}]},{"code":"46319","nom":"Théminettes","inscrits":177,"votants":107,"participation":60.45,"status":"elu","bord":"indecis","candidats":[{"nom":"Demain Théminettes Ecouter Agir Avancer","parti":"Demain Théminettes Ecouter Agir Avancer","bord":"Divers","score":100.0,"color":"var(--div)"}]},{"code":"46320","nom":"Tour-de-Faure","inscrits":339,"votants":254,"participation":74.93,"status":"elu","bord":"indecis","candidats":[{"nom":"Tour-de-Faure Avenir","parti":"Tour-de-Faure Avenir","bord":"Divers","score":64.08,"color":"var(--div)"},{"nom":"Ensemble vivons Tour-de-Faure","parti":"Ensemble vivons Tour-de-Faure","bord":"Divers","score":35.92,"color":"var(--div)"}]},{"code":"46321","nom":"Touzac","inscrits":307,"votants":269,"participation":87.62,"status":"elu","bord":"indecis","candidats":[{"nom":"Liste d'entente et d'intérêts communaux","parti":"Liste d'entente et d'intérêts communaux","bord":"Divers","score":53.67,"color":"var(--div)"},{"nom":"Ensemble pour Touzac","parti":"Ensemble pour Touzac","bord":"Divers","score":46.33,"color":"var(--div)"}]},{"code":"46322","nom":"Trespoux-Rassiels","inscrits":702,"votants":407,"participation":57.98,"status":"elu","bord":"indecis","candidats":[{"nom":"Continuons ensemble","parti":"Continuons ensemble","bord":"Divers","score":100.0,"color":"var(--div)"}]},{"code":"46323","nom":"Ussel","inscrits":79,"votants":61,"participation":77.22,"status":"elu","bord":"indecis","candidats":[{"nom":"ENSEMBLE POUR USSEL","parti":"ENSEMBLE POUR USSEL","bord":"Divers","score":100.0,"color":"var(--div)"}]},{"code":"46324","nom":"Uzech","inscrits":180,"votants":120,"participation":66.67,"status":"elu","bord":"indecis","candidats":[{"nom":"ENSEMBLE POUR NOTRE VILLAGE","parti":"ENSEMBLE POUR NOTRE VILLAGE","bord":"Divers","score":100.0,"color":"var(--div)"}]},{"code":"46328","nom":"Varaire","inscrits":294,"votants":207,"participation":70.41,"status":"elu","bord":"indecis","candidats":[{"nom":"Ensemble pour Varaire","parti":"Ensemble pour Varaire","bord":"Divers","score":100.0,"color":"var(--div)"}]},{"code":"46329","nom":"Vaylats","inscrits":296,"votants":247,"participation":83.45,"status":"elu","bord":"indecis","candidats":[{"nom":"REUNIR POUR REUSSIR","parti":"REUNIR POUR REUSSIR","bord":"Divers","score":74.9,"color":"var(--div)"},{"nom":"VAYLATS AUTREMENT","parti":"VAYLATS AUTREMENT","bord":"Divers","score":25.1,"color":"var(--div)"}]},{"code":"46330","nom":"Vayrac","inscrits":973,"votants":723,"participation":74.31,"status":"2t","bord":"indecis","candidats":[{"nom":"AVEC VOUS POUR VAYRAC","parti":"AVEC VOUS POUR VAYRAC","bord":"Divers","score":40.86,"color":"var(--div)"},{"nom":"VAYRAC, PRENDRE LE BON TOURNANT","parti":"VAYRAC, PRENDRE LE BON TOURNANT","bord":"Divers","score":31.29,"color":"var(--div)"},{"nom":"VAYRAC NOTRE CAP","parti":"VAYRAC NOTRE CAP","bord":"Divers","score":27.86,"color":"var(--div)"}]},{"code":"46332","nom":"Viazac","inscrits":286,"votants":162,"participation":56.64,"status":"elu","bord":"indecis","candidats":[{"nom":"VIAZAC : CONTINUONS ENSEMBLE","parti":"VIAZAC : CONTINUONS ENSEMBLE","bord":"Divers","score":100.0,"color":"var(--div)"}]},{"code":"46333","nom":"Vidaillac","inscrits":144,"votants":109,"participation":75.69,"status":"elu","bord":"indecis","candidats":[{"nom":"Ensemble l'avenir de Vidaillac","parti":"Ensemble l'avenir de Vidaillac","bord":"Divers","score":100.0,"color":"var(--div)"}]},{"code":"46334","nom":"Le Vigan-en-Quercy","inscrits":1364,"votants":771,"participation":56.52,"status":"elu","bord":"indecis","candidats":[{"nom":"AVEC VOUS POUR LE VIGAN-EN-QUERCY","parti":"AVEC VOUS POUR LE VIGAN-EN-QUERCY","bord":"Divers","score":100.0,"color":"var(--div)"}]},{"code":"46335","nom":"Villesèque","inscrits":349,"votants":236,"participation":67.62,"status":"elu","bord":"indecis","candidats":[{"nom":"Ensemble pour Villesèque","parti":"Ensemble pour Villesèque","bord":"Divers","score":100.0,"color":"var(--div)"}]},{"code":"46336","nom":"Vire-sur-Lot","inscrits":298,"votants":237,"participation":79.53,"status":"elu","bord":"indecis","candidats":[{"nom":"VIRE, UNIS POUR DEMAIN","parti":"VIRE, UNIS POUR DEMAIN","bord":"Divers","score":74.25,"color":"var(--div)"},{"nom":"ENSEMBLE POUR VIRE SUR LOT","parti":"ENSEMBLE POUR VIRE SUR LOT","bord":"Divers","score":25.75,"color":"var(--div)"}]},{"code":"46337","nom":"Mayrac","inscrits":228,"votants":194,"participation":85.09,"status":"elu","bord":"indecis","candidats":[{"nom":"MAYRAC UNIS POUR DEMAIN","parti":"MAYRAC UNIS POUR DEMAIN","bord":"Divers","score":60.33,"color":"var(--div)"},{"nom":"BIEN VIVRE A MAYRAC","parti":"BIEN VIVRE A MAYRAC","bord":"Divers","score":39.67,"color":"var(--div)"}]},{"code":"46338","nom":"Bessonies","inscrits":75,"votants":66,"participation":88.0,"status":"elu","bord":"indecis","candidats":[{"nom":"DYNAMISER NOTRE TERRITOIRE","parti":"DYNAMISER NOTRE TERRITOIRE","bord":"Divers","score":100.0,"color":"var(--div)"}]},{"code":"46339","nom":"Saint-Jean-Lagineste","inscrits":289,"votants":209,"participation":72.32,"status":"elu","bord":"indecis","candidats":[{"nom":"Bien Vivre Ensemble","parti":"Bien Vivre Ensemble","bord":"Divers","score":100.0,"color":"var(--div)"}]},{"code":"46340","nom":"Saint-Pierre-Lafeuille","inscrits":298,"votants":192,"participation":64.43,"status":"elu","bord":"indecis","candidats":[{"nom":"SAINT PIERRE LAFEUILLE AU COEUR","parti":"SAINT PIERRE LAFEUILLE AU COEUR","bord":"Divers","score":100.0,"color":"var(--div)"}]}]}